{"dokumentstatus":{"dokument":{"hangar_id":"5011711","dok_id":"H6022039","rm":"2018/19","beteckning":"2039","typ":"mot","subtyp":"Partimotion","doktyp":"mot","typrubrik":"Motion 2018/19:2039 av Jan Björklund m.fl. (L)","dokumentnamn":"Motion","debattnamn":"Motion","tempbeteckning":"L","organ":"SoU","mottagare":"","nummer":"2039","slutnummer":"0","datum":"2018-11-29 00:00:00","systemdatum":"2019-06-04 15:30:45","publicerad":"2018-11-29 00:00:00","titel":"Leva livet hela livet","subtitel":"av Jan Björklund m.fl. (L)","status":"Klar","htmlformat":"html","relaterat_id":"","source":"Filur","sourceid":"10e930f3-eabd-4174-93ef-f71a78ad5d2f","dokument_url_text":"http://data.riksdagen.se/dokument/H6022039/text","dokument_url_html":"http://data.riksdagen.se/dokument/H6022039","dokumentstatus_url_xml":"http://data.riksdagen.se/dokumentstatus/H6022039","html":"<style><!-- \r\n /********************************************************************************************************/\r\n/* Styles for D:\\Logs\\DocumentConverter\\\\Output_98ce4abb-43c5-464a-90de-79e084dfc98a\\HTML\\Dokument.html */\r\n/* Generated by Aspose.Words for .NET 15.3.0.0                                                          */\r\n/********************************************************************************************************/\r\n\r\n@page Section1 { size:595.3pt 841.9pt; margin:35.45pt 85.05pt }\r\ndiv.Section1 { page:Section1 }\r\ndiv.pconf body { t-i:17pt; line-height:15pt; font-family:'Verdana'; font-size: 0.90em }\r\ndiv.pconf h1, h2, h3, h4, h5, h6, p { margin:0pt }\r\ndiv.pconf li, table { margin-top:0pt; margin-bottom:0pt }\r\ndiv.pconf h1 { margin-top:41pt; margin-bottom:0pt; t-i:0pt; page-break-inside:avoid; page-break-after:avoid; line-height:19.5pt; font-family:'Verdana'; font-size: 1.05em; font-weight:normal }\r\ndiv.pconf h2 { margin-top:30pt; margin-bottom:0pt; t-i:0pt; page-break-inside:avoid; page-break-after:avoid; line-height:15pt; font-family:'Verdana'; font-size: 1.00em; font-weight:normal }\r\ndiv.pconf h3 { margin-top:18pt; margin-bottom:0pt; t-i:0pt; page-break-inside:avoid; page-break-after:avoid; line-height:15pt; font-family:'Verdana'; font-size: 0.90em; font-weight:bold }\r\ndiv.pconf h4 { margin-top:18pt; margin-bottom:0pt; t-i:0pt; page-break-inside:avoid; page-break-after:avoid; line-height:15pt; font-family:'Verdana'; font-size: 0.90em; font-weight:normal; font-style:italic }\r\ndiv.pconf h5 { margin-top:15pt; margin-bottom:0pt; t-i:0pt; page-break-inside:avoid; page-break-after:avoid; line-height:15pt; font-family:'Verdana'; font-size: 0.90em; font-weight:bold; font-style:normal }\r\ndiv.pconf h6 { margin-top:15pt; margin-bottom:0pt; t-i:0pt; page-break-inside:avoid; page-break-after:avoid; line-height:15pt; font-family:'Verdana'; font-size: 0.90em; font-weight:normal; font-style:italic }\r\n.Heading7 { margin-top:15pt; margin-bottom:0pt; t-i:0pt; page-break-inside:avoid; page-break-after:avoid; line-height:15pt; font-family:'Verdana'; font-size: 0.90em; font-weight:normal; font-style:italic }\r\n.Heading8 { margin-top:15pt; margin-bottom:0pt; t-i:0pt; page-break-inside:avoid; page-break-after:avoid; line-height:15pt; font-family:'Verdana'; font-size: 0.90em; font-weight:normal; font-style:italic }\r\n.Heading9 { margin-top:0pt; margin-bottom:0pt; t-i:0pt; page-break-inside:avoid; page-break-after:avoid; line-height:15pt; font-family:'Verdana'; font-size: 0.90em; font-weight:normal; font-style:italic }\r\n.BalloonText { margin-bottom:0pt; t-i:17pt; line-height:normal; font-family:'Segoe UI'; font-size: 0.90em }\r\n.Beteckning { margin-top:18pt; margin-bottom:0pt; t-i:14.2pt; page-break-inside:auto; page-break-after:auto; line-height:19.5pt; font-size: 1.05em }\r\n.BlockText, .Inramatstycke { margin-right:56.7pt; margin-left:56.7pt; margin-bottom:0pt; t-i:0pt; text-align:nojustify; line-height:15pt; border-top-style:solid; border-top-width:0.75pt; border-top-color:#000000; border-right-style:solid; border-right-width:0.75pt; border-right-color:#000000; border-left-style:solid; border-left-width:0.75pt; border-left-color:#000000; border-bottom-style:solid; border-bottom-width:0.75pt; border-bottom-color:#000000; padding-top:10pt; padding-right:10pt; padding-left:10pt; padding-bottom:10pt; font-size: 0.90em; font-style:italic }\r\n.Citaticitat { margin-top:7.5pt; margin-left:34pt; margin-bottom:0pt; t-i:0pt; line-height:12pt; font-size: 0.90em }\r\n.Citaticitatmedindrag { margin-top:0pt; margin-left:34pt; margin-bottom:7.5pt; t-i:17pt; line-height:12pt; font-size: 0.90em }\r\n.Citatmedindrag { margin-top:0pt; margin-left:17pt; margin-bottom:0pt; t-i:17pt; line-height:12pt; font-size: 0.90em }\r\n.CommentSubject { margin-bottom:0pt; t-i:17pt; line-height:normal; font-size: 0.90em; font-weight:bold }\r\n.CommentText { margin-bottom:0pt; t-i:17pt; line-height:normal; font-size: 0.90em }\r\n.FSHTitel, .Dokumentrubrik { margin-top:4pt; margin-bottom:4pt; t-i:0pt; page-break-inside:avoid; page-break-after:avoid; line-height:20pt; border-bottom-style:solid; border-bottom-width:0.75pt; border-bottom-color:#000000; padding-bottom:3pt; font-size: 1.05em }\r\n.FSHLogo { margin-top:4pt; margin-bottom:0pt; t-i:0pt; line-height:normal; font-size: 0.90em }\r\n.FSHNormL { margin-top:4pt; margin-bottom:0pt; t-i:0pt; line-height:15pt; border-top-style:solid; border-top-width:1.5pt; border-top-color:#000000; padding-top:3pt; font-size: 0.90em }\r\n.FSHNormal { margin-top:4pt; margin-bottom:0pt; t-i:0pt; line-height:15pt; font-size: 0.90em }\r\n.FSHNormalS5 { margin-top:11.5pt; margin-bottom:26pt; t-i:0pt; page-break-inside:avoid; page-break-after:avoid; line-height:12.5pt; font-size: 0.95em; font-weight:bold }\r\n.FSHRub1, .Rubrik1S5 { margin-top:135pt; margin-bottom:0pt; t-i:0pt; page-break-inside:avoid; page-break-after:avoid; line-height:16pt; font-size: 1.00em }\r\n.FSHRub2, .Rubrik1A4 { margin-top:50pt; margin-bottom:5pt; t-i:0pt; page-break-inside:avoid; page-break-after:avoid; line-height:24pt; font-size: 1.05em }\r\n.Footer { margin-top:4pt; margin-bottom:0pt; t-i:0pt; text-align:center; line-height:normal; font-size: 0.90em }\r\n.FootnoteText { margin-top:0pt; margin-bottom:0pt; t-i:0pt; line-height:12pt; font-size: 0.90em }\r\n.Yrkandehnv, .Frslagspunkthnv { margin-bottom:0pt; t-i:0pt; page-break-inside:avoid; page-break-after:avoid; font-size: 0.90em }\r\n.Frslagsrubrik { margin-top:41pt; margin-bottom:0pt; t-i:0pt; page-break-inside:avoid; page-break-after:avoid; line-height:19.5pt; font-family:'Verdana'; font-size: 1.05em }\r\n.Frslagstext, .Hemstlatt, .Yrkande { margin-top:4pt; margin-left:19.85pt; margin-bottom:0pt; t-i:-19.85pt; line-height:15pt; font-size: 0.90em }\r\n.Header { margin-top:4pt; margin-bottom:0pt; t-i:0pt; line-height:normal; font-size: 0.90em }\r\n.KantRubrikS5H { margin-top:6pt; margin-right:2.85pt; margin-bottom:0pt; t-i:0pt; text-align:right; line-height:8pt; font-size: 0.90em }\r\n.KantRubrikS5Hrad2 { margin-top:0pt; margin-right:2.85pt; margin-bottom:0pt; t-i:0pt; text-align:right; line-height:10pt; font-size: 0.90em }\r\n.KantRubrikS5V { margin-top:6pt; margin-right:0pt; margin-bottom:0pt; t-i:0pt; text-align:left; line-height:8pt; font-size: 0.90em }\r\n.KantRubrikS5Vrad2 { margin-top:0pt; margin-right:0pt; margin-bottom:0pt; t-i:0pt; text-align:left; line-height:10pt; font-size: 0.90em }\r\n.KantrubrikH { margin-top:4pt; margin-right:0pt; margin-bottom:0pt; t-i:0pt; text-align:right; line-height:15pt; font-size: 0.90em }\r\n.KantrubrikV { margin-top:4pt; margin-left:0pt; margin-bottom:0pt; t-i:0pt; line-height:normal; font-size: 0.90em }\r\n.Klla { margin-top:0pt; margin-bottom:0pt; t-i:0pt; line-height:12pt; font-size: 0.90em }\r\n.Lagtext { margin-top:4pt; margin-bottom:0pt; t-i:0pt; line-height:normal; font-size: 0.90em }\r\n.Lagtextindrag { margin-top:4pt; margin-bottom:0pt; t-i:14.2pt; line-height:normal; font-size: 0.90em }\r\n.Lagtextrubrik { margin-top:4pt; margin-bottom:0pt; t-i:0pt; line-height:normal; font-size: 0.90em; font-style:italic; letter-spacing:1pt }\r\n.List { margin-top:7.5pt; margin-left:17pt; margin-bottom:7.5pt; t-i:-17pt; line-height:15pt; font-size: 0.90em }\r\n.ListBullet, .PunktlistaBomb { margin-top:4pt; margin-left:14.2pt; margin-bottom:0pt; t-i:-14.2pt; line-height:15pt; font-size: 0.90em }\r\n.ListNumber, .PunktlistaNummer { margin-top:4pt; margin-left:14.2pt; margin-bottom:0pt; t-i:-14.2pt; line-height:15pt; font-size: 0.90em }\r\n.ListParagraph { margin-left:36pt; margin-bottom:0pt; t-i:17pt; line-height:15pt; font-size: 0.90em }\r\n.ListaGemener { margin-top:7.5pt; margin-left:17pt; margin-bottom:7.5pt; t-i:-17pt; line-height:15pt; font-size: 0.90em }\r\n.ListaLinje { margin-top:7.5pt; margin-left:17pt; margin-bottom:7.5pt; t-i:-17pt; line-height:15pt; font-size: 0.90em }\r\n.ListaNummer { margin-top:7.5pt; margin-left:17pt; margin-bottom:7.5pt; t-i:-17pt; line-height:15pt; font-size: 0.90em }\r\n.ListaPunkt { margin-top:7.5pt; margin-left:17pt; margin-bottom:7.5pt; t-i:-17pt; line-height:15pt; font-size: 0.90em }\r\n.MotionTIllRiksdagen { margin-top:18pt; margin-bottom:0pt; t-i:0pt; page-break-inside:avoid; page-break-after:avoid; line-height:19.5pt; font-size: 1.05em }\r\n.Motionr { margin-top:14pt; margin-bottom:31.5pt; t-i:0pt; page-break-inside:avoid; line-height:15pt; font-size: 1.00em; font-weight:bold; font-style:normal }\r\n.NormalIndent { margin-left:65.2pt; margin-bottom:0pt; t-i:17pt; line-height:15pt; font-size: 0.90em }\r\n.Normalutanindragellerluft { margin-top:4pt; margin-bottom:0pt; t-i:0pt; line-height:15pt; font-size: 0.90em }\r\n.Normal00 { margin-top:4pt; margin-bottom:0pt; t-i:0pt; line-height:normal; font-size: 0.90em }\r\n.NormalA4fot { margin-top:12pt; margin-bottom:0pt; t-i:0pt; text-align:center; line-height:normal; font-size: 0.90em }\r\n.NormalA4sidnr { margin-top:4pt; margin-bottom:12pt; t-i:0pt; text-align:center; line-height:normal; font-size: 0.90em }\r\n.NormalS5sidnrH { margin-top:4pt; margin-right:2.85pt; margin-bottom:0pt; t-i:0pt; text-align:right; line-height:normal; font-size: 0.90em }\r\n.NormalS5sidnrV { margin-top:4pt; margin-right:0pt; margin-bottom:0pt; t-i:0pt; text-align:left; line-height:normal; font-size: 0.90em }\r\n.PlainText { margin-bottom:0pt; t-i:0pt; line-height:12pt; font-family:'Verdana'; font-size: 0.90em }\r\n.Strecklista, .PunktlistaTankstreck { margin-top:4pt; margin-left:14.2pt; margin-bottom:0pt; t-i:-14.2pt; line-height:15pt; font-size: 0.90em }\r\n.Quote { margin-top:7.5pt; margin-left:17pt; margin-bottom:0pt; t-i:0pt; line-height:12pt; font-size: 0.90em }\r\n.R1 { margin-top:41pt; margin-bottom:0pt; t-i:0pt; page-break-inside:avoid; page-break-after:avoid; line-height:19.5pt; font-family:'Verdana'; font-size: 1.05em }\r\n.R2 { margin-top:30pt; margin-bottom:0pt; t-i:0pt; page-break-inside:avoid; page-break-after:avoid; line-height:15pt; font-family:'Verdana'; font-size: 1.00em }\r\n.R3 { margin-top:18pt; margin-bottom:0pt; t-i:0pt; page-break-inside:avoid; page-break-after:avoid; line-height:15pt; font-family:'Verdana'; font-size: 0.90em; font-weight:bold }\r\n.Rubrik1numrerat { margin-top:41pt; margin-left:18pt; margin-bottom:0pt; t-i:-18pt; page-break-inside:auto; page-break-after:avoid; line-height:19.5pt; font-family:'Verdana'; font-size: 1.05em }\r\n.Rubrik2numrerat { margin-top:30pt; margin-left:39.6pt; margin-bottom:0pt; t-i:-39.6pt; page-break-inside:avoid; page-break-after:avoid; line-height:15pt; font-family:'Verdana'; font-size: 1.00em }\r\n.Rubrik3numrerat { margin-top:18pt; margin-left:61.2pt; margin-bottom:0pt; t-i:-61.2pt; page-break-inside:avoid; page-break-after:avoid; line-height:15pt; font-family:'Verdana'; font-size: 0.90em; font-weight:bold }\r\n.Rubrik4numrerat { margin-top:18pt; margin-left:82.2pt; margin-bottom:0pt; t-i:-82.2pt; page-break-inside:avoid; page-break-after:avoid; line-height:15pt; font-family:'Verdana'; font-size: 0.90em; font-weight:normal; font-style:italic }\r\n.RubrikFrslagTIllRiksdagsbeslut { margin-top:41pt; margin-bottom:15pt; t-i:0pt; page-break-inside:avoid; page-break-after:avoid; line-height:19.5pt; font-family:'Verdana'; font-size: 1.05em }\r\n.RubrikInnehllsf { margin-top:41pt; margin-bottom:0pt; t-i:0pt; page-break-inside:avoid; page-break-after:avoid; line-height:19.5pt; font-family:'Verdana'; font-size: 1.05em }\r\n.RubrikSammanf { margin-top:41pt; margin-bottom:0pt; t-i:0pt; page-break-inside:avoid; page-break-after:avoid; line-height:19.5pt; font-family:'Verdana'; font-size: 1.05em }\r\n.Salutation { margin-top:41pt; margin-bottom:0pt; t-i:0pt; page-break-inside:avoid; page-break-after:avoid; line-height:19.5pt; font-family:'Verdana'; font-size: 1.05em }\r\n.Streckkod { margin-top:12pt; margin-bottom:0pt; t-i:0pt; text-align:center; line-height:normal; font-family:IDAutomationHC39S; font-size: 1.00em }\r\n.Subtitle { margin-top:4pt; margin-bottom:0pt; t-i:0pt; line-height:15pt; font-family:'Verdana'; font-size: 0.90em; font-weight:bold }\r\n.TOC1 { margin-top:4pt; margin-bottom:0pt; t-i:0pt; line-height:15pt; font-size: 0.90em }\r\n.TOC2 { margin-top:4pt; margin-left:14.2pt; margin-bottom:0pt; t-i:0pt; line-height:15pt; font-size: 0.90em }\r\n.TOC3 { margin-top:4pt; margin-left:28.35pt; margin-bottom:0pt; t-i:0pt; line-height:15pt; font-size: 0.90em }\r\n.TOC4 { margin-top:4pt; margin-left:42.55pt; margin-bottom:0pt; t-i:0pt; line-height:15pt; font-size: 0.90em }\r\n.TOC5 { margin-top:4pt; margin-left:56.7pt; margin-bottom:0pt; t-i:0pt; line-height:15pt; font-size: 0.90em }\r\n.TOC6 { margin-top:4pt; margin-left:56.7pt; margin-bottom:0pt; t-i:0pt; line-height:15pt; font-size: 0.90em }\r\n.TOC7 { margin-top:15pt; margin-left:56.7pt; margin-bottom:0pt; t-i:14.2pt; page-break-inside:avoid; page-break-after:avoid; line-height:normal; font-family:'Verdana'; font-size: 0.90em; font-weight:normal; font-style:italic }\r\n.TOC8 { margin-top:15pt; margin-left:56.7pt; margin-bottom:0pt; t-i:14.2pt; page-break-inside:avoid; page-break-after:avoid; line-height:normal; font-family:'Verdana'; font-size: 0.90em; font-weight:normal; font-style:italic }\r\n.TOC9 { margin-top:15pt; margin-left:56.7pt; margin-bottom:0pt; t-i:14.2pt; page-break-inside:avoid; page-break-after:avoid; line-height:normal; font-family:'Verdana'; font-size: 0.90em; font-weight:normal; font-style:italic }\r\n.TOCHeading { margin-top:41pt; margin-bottom:0pt; t-i:0pt; page-break-inside:avoid; page-break-after:avoid; line-height:19.5pt; font-family:'Verdana'; font-size: 1.05em }\r\n.Tabellunderrubrik { margin-top:0pt; margin-bottom:0pt; t-i:0pt; line-height:15pt; font-size: 0.90em; font-weight:normal; font-style:italic }\r\n.Tabellrubrik { margin-top:7.5pt; margin-bottom:0pt; t-i:0pt; line-height:15pt; font-size: 0.90em; font-weight:bold }\r\n.Title { margin-top:41pt; margin-bottom:0pt; t-i:0pt; page-break-inside:avoid; page-break-after:avoid; line-height:19.5pt; font-family:'Verdana'; font-size: 1.05em }\r\n.Underskriftdatum { margin-top:24pt; margin-bottom:3pt; t-i:0pt; page-break-inside:avoid; line-height:15pt; font-size: 0.90em; font-style:normal }\r\n.Underskrifter { margin-top:15pt; margin-bottom:3pt; t-i:0pt; page-break-inside:avoid; line-height:15pt; font-size: 0.90em; font-style:italic }\r\nspan.BallongtextChar { font-family:'Segoe UI'; font-size: 0.90em }\r\nspan.BeteckningChar { font-size:19.5pt }\r\nspan.CommentReference { font-size:8pt }\r\nspan.FSHRub2Char, span.Rubrik1A4Char { font-size:24pt }\r\nspan.FotnotstextChar { font-size:10pt }\r\nspan.InledningChar { font-family:'Verdana'; font-size: 1.00em; font-weight:bold }\r\nspan.IntenseReference { font-weight:normal; font-style:normal; font-variant:normal; text-decoration:none; text-transform:none; letter-spacing:0pt; vertical-align:0pt; color:#000000; display:inline }\r\nspan.KommentarerChar { font-size:10pt }\r\nspan.KommentarsmneChar { font-size:10pt; font-weight:bold }\r\nspan.MotionTIllRiksdagenChar { font-size:19.5pt }\r\nspan.OformateradtextChar { font-family:'Verdana'; font-size: 0.90em }\r\nspan.PlaceholderText { color:#f4b083 }\r\nspan.Rubrik1Char { font-family:'Verdana'; font-size: 1.05em }\r\nspan.Rubrik2Char { font-family:'Verdana'; font-size: 1.00em; font-weight:bold }\r\nspan.Rubrik3Char { font-family:'Verdana'; font-size: 0.90em; font-weight:bold }\r\nspan.Rubrik4Char { font-family:'Verdana'; font-size: 0.90em; font-style:italic }\r\nspan.Rubrik5Char { font-family:'Verdana'; font-weight:bold }\r\nspan.Rubrik6Char { font-family:'Verdana'; font-style:italic }\r\nspan.Rubrik7Char { font-family:'Verdana'; font-size: 0.90em; font-weight:bold }\r\nspan.Rubrik8Char { font-family:'Verdana'; font-size: 0.90em; font-weight:bold }\r\nspan.Rubrik9Char { font-family:'Verdana'; font-size: 0.90em; font-weight:bold }\r\nspan.RubrikChar { font-family:'Verdana'; font-size: 1.00em; font-weight:bold }\r\nspan.SidfotChar { font-size:11.5pt }\r\nspan.UnderrubrikChar { font-family:'Verdana'; font-size: 0.90em; font-weight:bold }\r\n.TableGrid {  }\r\n\r\n.pconf{width: 450px;margin-left:5px;overflow:visable;font-family:Verdana, Geneva, sans-serif;} \r\n .sidhuvud_publikation, .sidhuvud_beteckning{font-size:133%}\r\n.MotionarLista {font-size:122%}\r\n\r\n--></style><div class=\"pconf\"><span class=\"sidhuvud_publikation\">Motion till riksdagen</span><br/>\r\n<span class=\"sidhuvud_beteckning\">2018/19:2039</span><br/>\r\n<span class=\"MotionarLista\">av Jan Björklund m.fl. (L)</span><br/>\r\n<h1>Leva livet hela livet</h1>\r\n<hr class=\"sidhuvud_linje\"/>\r\n\r\n\r\n\t\t<div class=\"Section1\">\r\n\t\t\t<h1 style=\"margin-bottom:15pt; -aw-sdt-tag:CC_Boilerplate_4; -aw-sdt-title:CC_Boilerplate_4\">\r\n\t\t\t\t<span>Förslag till riksdagsbeslut</span>\r\n\t\t\t</h1>\r\n\t\t\t<ol type=\"1\" style=\"margin:0pt; padding-left:0pt\">\r\n\t\t\t\t<li class=\"Frslagstext\" style=\"margin-left:14pt; t-i:0pt; padding-left:5.85pt; font-family:'Verdana'; font-size: 0.90em\">\r\n\t\t\t\t\t<span style=\"font-family:'Verdana'; font-size: 0.90em\">Riksdagen ställer sig bakom det som anförs i motionen om en systematisk genomgång av anmälningar om åldersdiskriminering och tillkännager detta för regeringen.</span>\r\n\t\t\t\t</li>\r\n\t\t\t\t<li class=\"Frslagstext\" style=\"margin-left:14pt; t-i:0pt; padding-left:5.85pt; font-family:'Verdana'; font-size: 0.90em\">\r\n\t\t\t\t\t<span style=\"font-family:'Verdana'; font-size: 0.90em\">Riksdagen ställer sig bakom det som anförs i motionen om att på sikt höja gränsen för rätten att stanna kvar i arbetslivet till 71 år och tillkännager detta för regeringen.</span>\r\n\t\t\t\t</li>\r\n\t\t\t\t<li class=\"Frslagstext\" style=\"margin-left:14pt; t-i:0pt; padding-left:5.85pt; font-family:'Verdana'; font-size: 0.90em\">\r\n\t\t\t\t\t<span style=\"font-family:'Verdana'; font-size: 0.90em\">Riksdagen ställer sig bakom det som anförs i motionen om att ökad hälsa på äldre dar bör inarbetas i strategierna för folkhälsopolitiken och tillkännager detta för regeringen.</span>\r\n\t\t\t\t</li>\r\n\t\t\t\t<li class=\"Frslagstext\" style=\"margin-left:14pt; t-i:0pt; padding-left:5.85pt; font-family:'Verdana'; font-size: 0.90em\">\r\n\t\t\t\t\t<span style=\"font-family:'Verdana'; font-size: 0.90em\">Riksdagen ställer sig bakom det som anförs i motionen om att justera åldersgränserna för screeningprogram och tillkännager detta för regeringen.</span>\r\n\t\t\t\t</li>\r\n\t\t\t\t<li class=\"Frslagstext\" style=\"margin-left:14pt; t-i:0pt; padding-left:5.85pt; font-family:'Verdana'; font-size: 0.90em\">\r\n\t\t\t\t\t<span style=\"font-family:'Verdana'; font-size: 0.90em\">Riksdagen ställer sig bakom det som anförs i motionen om att förbättra informationen om tandvårdsstöden och tillkännager detta för regeringen.</span>\r\n\t\t\t\t</li>\r\n\t\t\t\t<li class=\"Frslagstext\" style=\"margin-left:14pt; t-i:0pt; padding-left:5.85pt; font-family:'Verdana'; font-size: 0.90em\">\r\n\t\t\t\t\t<span style=\"font-family:'Verdana'; font-size: 0.90em\">Riksdagen ställer sig bakom det som anförs i motionen om förstärkt kunskapsstyrning av äldretandvården och tillkännager detta för regeringen.</span>\r\n\t\t\t\t</li>\r\n\t\t\t\t<li class=\"Frslagstext\" style=\"margin-left:14pt; t-i:0pt; padding-left:5.85pt; font-family:'Verdana'; font-size: 0.90em\">\r\n\t\t\t\t\t<span style=\"font-family:'Verdana'; font-size: 0.90em\">Riksdagen ställer sig bakom det som anförs i motionen om en översyn av tandvårdssystemet och tillkännager detta för regeringen.</span>\r\n\t\t\t\t</li>\r\n\t\t\t\t<li class=\"Frslagstext\" style=\"margin-left:14pt; t-i:0pt; padding-left:5.85pt; font-family:'Verdana'; font-size: 0.90em\">\r\n\t\t\t\t\t<span style=\"font-family:'Verdana'; font-size: 0.90em\">Riksdagen ställer sig bakom det som anförs i motionen om att inflytande över måltider bör tillhöra en skälig levnadsnivå och tillkännager detta för regeringen.</span>\r\n\t\t\t\t</li>\r\n\t\t\t\t<li class=\"Frslagstext\" style=\"margin-left:14pt; t-i:0pt; padding-left:5.85pt; font-family:'Verdana'; font-size: 0.90em\">\r\n\t\t\t\t\t<span style=\"font-family:'Verdana'; font-size: 0.90em\">Riksdagen ställer sig bakom det som anförs i motionen om organisationen av äldresjukvården och tillkännager detta för regeringen.</span>\r\n\t\t\t\t</li>\r\n\t\t\t\t<li class=\"Frslagstext\" style=\"margin-left:19.85pt; t-i:0pt; font-family:'Verdana'; font-size: 0.90em\">\r\n\t\t\t\t\t<span style=\"font-family:'Verdana'; font-size: 0.90em\">Riksdagen ställer sig bakom det som anförs i motionen om en nationell handlingsplan mot våld och övergrepp mot årsrika och tillkännager detta för regeringen.</span>\r\n\t\t\t\t</li>\r\n\t\t\t\t<li class=\"Frslagstext\" style=\"margin-left:19.85pt; t-i:0pt; font-family:'Verdana'; font-size: 0.90em\">\r\n\t\t\t\t\t<span style=\"font-family:'Verdana'; font-size: 0.90em\">Riksdagen ställer sig bakom det som anförs i motionen om anmälningsskyldighet vid misstanke om våld mot årsrika för personal inom vård och omsorg och tillkännager detta för regeringen.</span>\r\n\t\t\t\t</li>\r\n\t\t\t\t<li class=\"Frslagstext\" style=\"margin-left:19.85pt; t-i:0pt; font-family:'Verdana'; font-size: 0.90em\">\r\n\t\t\t\t\t<span style=\"font-family:'Verdana'; font-size: 0.90em\">Riksdagen ställer sig bakom det som anförs i motionen om förbättrat anhörigstöd och tillkännager detta för regeringen.</span>\r\n\t\t\t\t</li>\r\n\t\t\t</ol>\r\n\t\t\t<h1 style=\"-aw-sdt-tag:CC_Motivering_Rubrik; -aw-sdt-title:CC_Motivering_Rubrik\">\r\n\t\t\t\t<a name=\"MotionsStart\"></a><span>Motivering</span>\r\n\t\t\t</h1>\r\n\t\t\t<p class=\"Normalutanindragellerluft\">\r\n\t\t\t\t<span>Liberal politik innebär att var och en av oss ska ha rätt att bestämma över våra liv, så länge det inte inkräktar på någon annans frihet. Den rätten gäller hela livet igenom, också för den mest årsrika generationen. </span>\r\n\t\t\t</p>\r\n\t\t\t<p>\r\n\t\t\t\t<span>Årsrika människor har alltför länge betraktats som ett kollektiv och inte som de individer de är och som blir mer och mer olika varandra under livets gång och som vet bäst hur de vill ha det. Årsrika ses också som en tärande del av samhället trots att de långt upp i åren utgör en tillgång. För att understryka det använder vi ordet årsrik som synonym till gammal och äldre. Det betecknar att det handlar om människor som är rika på antal levda år,</span><span> </span><span>kunskap och livserfarenhet. Att öka årsrika människors självbestäm</span><span>­</span><span>mande och valmöjligheter är en central uppgift i Liberalernas äldrepolitik.</span>\r\n\t\t\t</p>\r\n\t\t\t<h2>\r\n\t\t\t\t<span>Ålderismen det största hindret för årsrika människors fria val</span>\r\n\t\t\t</h2>\r\n\t\t\t<p class=\"Normalutanindragellerluft\">\r\n\t\t\t\t<span>Det har gått 70 år sedan</span><span> </span><span>FN:s generalförsamling antog deklarationen om de mänskliga rättigheterna, om människors lika värde.</span><span> I Sverige förtydligas detta i d</span><span>iskriminerings</span><span>­</span><span>lagen (2008:567). Den syftar till att motverka diskriminering och främja lika rättigheter och möjligheter oavsett kön, </span><span>könsöverskridande identitet eller uttryck, etnisk tillhörig</span><span>­</span><span>het, religion eller annan trosuppfattning, funktionedsättning eller ålder.</span>\r\n\t\t\t</p>\r\n\t\t\t<p>\r\n\t\t\t\t<span>Diskriminering på grund av ålder, ålderism, har förekommit i alla tider men kommit i fokus under senare år. Begreppet ålderism betecknar ålder som grund för fördomar och nedvärdering av årsrika människor inom samhällets alla sektorer. Främst är det inom arbetsliv, tillgång till varor och tjänster samt hälso-</span><span> </span><span>och sjukvård den gör sig gällande.</span><span> </span><span>Världshälsoorganisationen (WHO)</span><span> </span><span>driver under perioden </span><span>2016–</span><span>2020 en kampanj mot ålderism och dess konsekvens åldersdiskriminering. WHO konstaterar utifrån data i World Values Survey att respekten för årsrika människor är lägst i höginkomstländerna och att det kan leda till sämre hälsa hos denna generation. Projektet </span><span>Cost 2014–</span><span>2018 finansierat av EU har gått igenom den forskning som finns om ålderism inom bl.a. arbetsliv, hälso- och sjukvård, medierna och lagstiftningen. Slutsatsen är att ålderismen förorsakar allvarliga konsekvenser inom samtliga områden.</span><span> </span><span>AGE Platform Europe, EU:s paraplyorganisationer för äldreorganisationer inom EU, driver hösten 2018 en kampanj mot ålderi</span><span>sm och lyfter här fram ålderis</span><span>mens konsekvenser inom diskrimi</span><span>­</span><span>neringsområdena kön, sociala rättigheter, migration, etnicitet, våld och övergrepp, religion och funktionsnedsättningar.</span>\r\n\t\t\t</p>\r\n\t\t\t<p>\r\n\t\t\t\t<span>I Sverige breddades 2013 d</span><span>iskrimineringslagen från att omfatta arbetsliv och utbildning till att också täcka hälso- och sjukvård, s</span><span>ocialtjänst</span><span>, boende m.m. Den är en viktig normsändare. Under tiden 2013–</span><span>2</span><span>017 mottog DO 1</span><span> </span><span>228 anmä</span><span>lningar om åldersdiskriminering.</span><span> 712 gällde arbetslivet, 228 varor och tjänster och 85 hälso- och sjukvård. Endast tre ledde till domstolsutslag och gällde chaufförer som fyllt 70 år och </span><span>nekats fortsätta köra buss respektive</span><span> färdtjänstfordon. De fick rätt i domstolen. Fyra ytterligare fall gick till förlikning. De hade nekats anställning på grund av ålder.</span><span> </span>\r\n\t\t\t</p>\r\n\t\t\t<p>\r\n\t\t\t\t<span>Innehållet i övriga anmälningar har inte föranlett någon åtgärd då de </span><span>inte anse</span><span>tt</span><span>s ligga inom ramen för lagstiftningen. Samtidigt kan vi konstatera att anmälarna känt sig åldersdiskriminerade. Vi anser att en systematisk genomgång av anmälningarna behöver göras med syfte att åtgärda orsakerna bakom att människor upplevt sig diskriminerade på grund av sin kronologiska ålder, och om så behövs </span><span>bör man </span><span>överväga att förtydliga lagen. </span>\r\n\t\t\t</p>\r\n\t\t\t<p>\r\n\t\t\t\t<span>Motsvarande gäller också för anmälningar som hör till andra diskriminerings</span><span>­</span><span>grunder. Vi </span><span>beskriver </span><span>i en annan motion hur </span><span>diskrimineringslagens utformning och DO:s funktion</span><span> bör </span><span>utvecklas</span><span>.</span>\r\n\t\t\t</p>\r\n\t\t\t<h2>\r\n\t\t\t\t<span>Längre arbetsliv för fler</span>\r\n\t\t\t</h2>\r\n\t\t\t<p class=\"Normalutanindragellerluft\">\r\n\t\t\t\t<span>En liberal utgångspunkt är att människor ska få fortsätta i arbetslivet så länge de vill och kan. Att känna sig behövd, att vara en del av samhä</span><span>llslivet, är för många en viktig</span><span> livskvalitetsfråga. Det finns dessutom gediget stöd i forskningen för att det är bra för </span><span>hälsan att få känna sig behövd – </span><span>också i sin yrkesidentitet.</span><span> </span><span>Det ger också dem som jobbar en bättre ekonomi och är samtidigt viktigt för samhällsekonomin i stort. Vi måste ta vara på den tillgång som årsrika personer utgör i arbetslivet. Vi anser därför att rätten att vara kvar i arbetslivet </span><span>på sikt </span><span>bör höjas till 71 års ålder. </span>\r\n\t\t\t</p>\r\n\t\t\t<p>\r\n\t\t\t\t<span>För att uppmuntra fler att jobba längre föreslår vi i vår budgetmotion att ålders</span><span>­</span><span>gränsen för det förhöjda jobbskatteavdraget för äldre </span><span>sänks från 65 till 63 års ålder</span><span> samt att den särskilda löneskatten för äldre avskaffas.</span>\r\n\t\t\t</p>\r\n\t\t\t<p>\r\n\t\t\t\t<span>Även om arbetsmiljön framför allt i fysiskt tunga arbeten förbättrats finns det fortfarande arbeten som är både fysiskt och psykiskt slitsamma och som gör det svårt för en del att orka arbeta högre upp i åldrarna. För dem ska det vara möjligt att gå i pension tidigare men också att erbjudas fortbildning och ändrade arbetsuppgifter så att de orkar arbeta längre, inte minst för att få bättre pension.</span>\r\n\t\t\t</p>\r\n\t\t\t<h2>\r\n\t\t\t\t<span>A</span><span>tt förebygga ohälsa bland årsrika människor</span>\r\n\t\t\t</h2>\r\n\t\t\t<p class=\"Normalutanindragellerluft\">\r\n\t\t\t\t<span>Under de</span><span> senaste 100 åren har vi lagt ett kvarts sekel till vår medellivslängd. Att vi lever längre och med många friska år är en av välfärdssamhällets viktigaste landvinningar.</span>\r\n\t\t\t</p>\r\n\t\t\t<p>\r\n\t\t\t\t<span>Vår politik syftar till att de friska åren ska bli fler, och att öka självständigheten och egenmakten för dem som behöver stöd. Viktigt för hälsa och livskvalitet är enligt Världshälsoorganisationen (WHO)</span><span> </span><span>att känna sig behövd. Där spelar arbetslivet men också det civila samhället en viktig roll. </span>\r\n\t\t\t</p>\r\n\t\t\t<p>\r\n\t\t\t\t<span>Forskning har visat att mycket står att vinna både för individerna själva och för samhällsekonomin genom skadeförebyggande åtgärder, fysisk aktivitet,</span><span> </span><span>hjälp till rökstopp, hjälp mot överbruk av alkohol, främjande av gott näringstillstånd, god tandhälsa och optimal läkemedelsbehandling. Detta gäller inte minst årsrika personer. </span>\r\n\t\t\t</p>\r\n\t\t\t<p>\r\n\t\t\t\t<span>Till hälsofrämjande insatser kan också rehabilitering efter skador och sjukdom av olika slag räknas. Här brister tillgången på träning för vardagliga aktiviteter. Välfunger</span><span>­</span><span>ande rehabiliteringsinsatser kräver samverkan mellan huvudmän och mellan personer</span><span>,</span><span> och sådan saknas på många håll. Endast 60 av landets kommuner har en medicinskt ansvarig fysioterapeut eller arbetsterapeut. Vi anser att det i kommunerna bör finnas en MAR, medicinsk</span><span>t</span><span> ansvarig för rehabilitering, vid sidan om MAS, medicinsk</span><span>t</span><span> ansvarig sjuksköterska, för att underlätta och påskynda rehabiliteringen av årsrika människor efter sjukdom och skador.</span>\r\n\t\t\t</p>\r\n\t\t\t<p>\r\n\t\t\t\t<span>I juni 2018 beslöt r</span><span>iksdagen att folkhälsopolitikens elva målområden skulle omvandlas till åtta. Medan det tidiga livets villkor utgör ett eget mål saknas ett mål för generationen årsrika människor. Vi menar att det är en stor brist. Olika faser i livet kräver olika fokus och strategier. På samma sätt som det behövs särskilda strategier för det tidiga livets villkor behövs det ett särskilt fokus för den som närmar sig sista sträckan på livsresan. När det inte blev något eget folkhälsomål för generationen årsrika människor bör målsättningen ökad hälsa på äldre dar inarbetas i de strategier som nu utvecklas för de olika målområdena.</span>\r\n\t\t\t</p>\r\n\t\t\t<h3>\r\n\t\t\t\t<span>Åldersgränser för screeningprogram</span>\r\n\t\t\t</h3>\r\n\t\t\t<p class=\"Normalutanindragellerluft\">\r\n\t\t\t\t<span>Screening för tidig upptäckt av vissa sjukdomar är en förebyggande insats som visat sig av stort värde</span><span>,</span><span> men här är de kronologiska åldersgränser som satts upp ett problem. Eftersom screening ska vara evidensbaserad har riktlinjer utfärdats inom ramen för de åldersgrupper forskarna valt att studera, inte utifrån i vilka åldersgrupper en sjukdom uppträder. Här</span><span> följer</span><span> två exempel.</span>\r\n\t\t\t</p>\r\n\t\t\t<p>\r\n\t\t\t\t<span>Mammografi för tidig upptäckt av bröstcancer erbjuds</span><span> </span><span>kvinnor i åldersgruppen 40–</span><span>74 år trots att bröstcance</span><span>r är vanlig hos kvinnor 75</span><span> </span><span>+. Åldersgruppen var vald av praktiska skäl. För tidig upptäckt av cancer i änd- och tjocktarm rekommenderas screening vartannat år för kvinno</span><span>r och män i åldersgruppen 60–</span><span>74 år eftersom tidig upptäckt av cancern uppskattas minska dödligheten med 15 procent. Åldersgruppen är vald därför att medelåldern för insjuknande är drygt 70 år men det finns studier som visar att screening kan vara värdefull också för dem som är yngre än 60 år.</span>\r\n\t\t\t</p>\r\n\t\t\t<p>\r\n\t\t\t\t<span>Statens medicinsk-</span><span>etiska råd, Smer, har i ett remissvar till Socialstyrelsen</span><span> tagit upp att de åldersgränser</span><span> som använts i de randomiserade studier Socialstyrel</span><span>sens rekommen</span><span>­</span><span>dationer bygger på</span><span> kan vara åldersdiskriminerande och leda till eventuell åldersdiskri</span><span>­</span><span>minering när resultaten omsätts i praktiska rekommendationer. </span>\r\n\t\t\t</p>\r\n\t\t\t<p>\r\n\t\t\t\t<span>Vi anser att de etiska aspekterna på åldersgränser vid screening för olika hälso</span><span>­</span><span>aspekter måste tas med vid utfärdande av rekommendationer om vilka som ska få tillgång till screening. Därför bör åldersgränsen för erbjudande av mammografi justeras upp och den för colon- och ändtarmscancer nedåt.</span>\r\n\t\t\t</p>\r\n\t\t\t<h2>\r\n\t\t\t\t<span>Tandhälsa </span>\r\n\t\t\t</h2>\r\n\t\t\t<p class=\"Normalutanindragellerluft\">\r\n\t\t\t\t<span>Idag är det få årsrika människor som inte har kvar sina tänder och är i behov av lös</span><span>­</span><span>tänder. De är vad tandläkare brukar säga ”betandade” med många egna tänder men en hög andel av dessa tänder är inte intakta utan har omfattande tidigare lagningar som kronor, broar och implantat. De löper högre risk än yngre att drabbas av karies och tandköttsinflammation. De kan ha sjukdomar som påverkar tandhälsan och de kan använda läkemedel som medför muntorr</span><span>het. Detta kan leda till smärta och</span><span> undernäring på grund av svårigheter att tugga, bita och svälja. De kan uppleva försämrad livskvalitet på grund av utseendeförändringar, andedräkt, talsvårigheter och infektioner. </span>\r\n\t\t\t</p>\r\n\t\t\t<p>\r\n\t\t\t\t<span>Historiskt har sjukdomar i munhålan på grund av tandproblem inte </span><span>subventionerats på samma sätt som hälso- och sjukvård. Den enskilde får bära en betydligt större del av kostnaden själv. E</span><span>n ny tand kan </span><span>innebära en utgift på</span><span> mellan 8</span><span> </span><span>000 och 12</span><span> </span><span>000 kronor medan man för ny höftled, ny knäled och ny ögonlins betalar sjukvårdsavgi</span><span>ft upp till högkostnadsskydd (1</span><span> </span><span>100 kr/år) samt 100 kr per vårddag på sjukhus.</span>\r\n\t\t\t</p>\r\n\t\t\t<p>\r\n\t\t\t\t<span>Vissa årsrika och vissa ingrepp i tänderna omfattas ibland av särskilda stöd som till exempel det till nödvändig tandvård, men till exempel Vårdanalys rapport Tandlösa tandvårdsstöd (2015:3) visar att det når ganska få, och inte ens alla som skulle ha rätt till det. Det här innebär att årsrika människor med låga pensioner av kostnadsskäl tvingas avstå från den tandvård de behöver med de hälsorisker det medför. </span>\r\n\t\t\t</p>\r\n\t\t\t<p>\r\n\t\t\t\t<span>Vi föreslår i vår budgetmotion att de medel som regeringen </span><span>lagt på att höja </span><span>tand</span><span>­</span><span>vårdsbidraget </span><span>och införa avgiftsfri tandvård för unga vuxna </span><span>i stället ska användas för att förstärka högkostnadsskyddet, och därmed minska kostnaderna för dem med allra dyrast tandvård. </span>\r\n\t\t\t</p>\r\n\t\t\t<p>\r\n\t\t\t\t<span>Rekommendationerna ur Tandlösa tandvårdsstöd bör genomföras. De handlar om att förbättra informationen om tandvårdsstöden så att fler får del av dem, att förstärka kunskapsstyrningen i äldretandvården samt att göra en översyn av h</span><span>ur tandvårds</span><span>­</span><span>systemet kan förenklas. Vi menar därutöver att en sådan översyn bör se över gränsdrag</span><span>­</span><span>ningarna för tandvårdsstöden, så att till exempel nödvändiga implantat av tänder kan jämställas med implantat av höftleder, knäleder och ögonlinser.</span>\r\n\t\t\t</p>\r\n\t\t\t<h2>\r\n\t\t\t\t<span>Psykisk ohälsa </span><span>bland årsrika</span>\r\n\t\t\t</h2>\r\n\t\t\t<p class=\"Normalutanindragellerluft\">\r\n\t\t\t\t<span>Socialstyrelsen har hösten 2018 publicerat en rapport om att psykisk ohälsa fortfarande är vanligare bland äldre liksom suicid bland äldre män. En tredjedel av alla över 65 år har vårdats för psykisk sjukdom alternativt använt psykofarmaka. Det föreligger stora variationer över landet. Bakom detta ligger bl.a. att personer 65 år eller äldre med psykisk ohälsa mer sällan träffar en specialist utan den vård de får lämnas oftast i primärvården. I primärvården är kunskaperna om äldrepsykiatri generellt sett dålig</span><span>a,</span><span> och i Sverige finns endast sex specialister i äldrepsykiatri. </span>\r\n\t\t\t</p>\r\n\t\t\t<p>\r\n\t\t\t\t<span>Vi anser att kunskaperna om årsrika människors psykiska hälsa och behov av kunskapsbaserad vård måste stärkas. Äldrepsykiatrin i Sverige måste utvecklas och ingå som en del i läkarutbildningen både i grundutbildningen och i specialistutbildningen av allmänläkare. Läkemedelsbehandling av årsrika patienter, särskilt med psykofarmaka, är omfattande bland årsrika patienter</span><span>,</span><span> och utbildning om hur läkemedel ska förskrivas för dem är en väsentlig del.</span>\r\n\t\t\t</p>\r\n\t\t\t<p>\r\n\t\t\t\t<span>Särskilt viktigt är det att finna orsakerna till en årsrik patients psykiska problem och inte begränsa insatserna till att behandla symtom. Det kan vara ensamhet som är orsaken till problemen och här löser inte läkemedelsbehandling situationen. </span>\r\n\t\t\t</p>\r\n\t\t\t<p>\r\n\t\t\t\t<span>Vår kunskap om orsakerna bakom suicid bland äldre, särskilt män</span><span>,</span><span> är begränsad. Det är därför viktigt att inträffade fall blir föremål för utredning av deras situation tiden före dödsfallet. Vi måste ha den kunskapen så att vi bättre kan förebygga att årsrika människor avslutar sina liv på detta sätt. </span>\r\n\t\t\t</p>\r\n\t\t\t<h2>\r\n\t\t\t\t<span>Funktionsnedsättning bland årsrika</span>\r\n\t\t\t</h2>\r\n\t\t\t<h3 style=\"margin-top:6pt\">\r\n\t\t\t\t<span>Döva och personer med hörselnedsättning </span>\r\n\t\t\t</h3>\r\n\t\t\t<p class=\"Normalutanindragellerluft\">\r\n\t\t\t\t<span>Med åldern försämras hörseln inte minst hos dem som utsatts för höga ljud tidigare i livet. </span>\r\n\t\t\t</p>\r\n\t\t\t<p>\r\n\t\t\t\t<span>För dem kan bakgrundsmusik i </span><span>radio- och tv</span><span>-program göra det omöjligt att höra vad som sägs. Också trafikbuller eller annat buller i bostaden kan försvåra hörandet. Detta bör uppmärksammas av programproducenter och bostadsbyggare. Bostäder bör byggas så att överhörning av trafikbuller från trafik utanför huset och ljud mellan lägenheterna inte kan ske.</span>\r\n\t\t\t</p>\r\n\t\t\t<p>\r\n\t\t\t\t<span>Döva har teckenspråk som främsta kommunikationsspråk. Teckenspråk används på samma sätt som hörande anvä</span><span>nder talspråk. År 1981 erkände r</span><span>iksdagen teckenspråket i Sverige som eget språk. </span>\r\n\t\t\t</p>\r\n\t\t\t<p>\r\n\t\t\t\t<span>Idag finns i Sverige bara ett par äldreboenden där det finns personal som kan teckenspråk. Det innebär att många döva personer blir isolerade när de inte kan kommunicera med personal och boende därför att det fattas någon i deras närhet som behärskar teckenspråk. Årsrika döva berövas därmed sin identitet och riskerar att drabbas av depression och ångest när kommunikationen brister. Också i hemtjänsten är det problematiskt om det inte finns tillgång till någon som behärskar teckenspråk.</span>\r\n\t\t\t</p>\r\n\t\t\t<p>\r\n\t\t\t\t<span>Kunskapsbristen vad gäller årsrika döva personers behov är stor inom kommunerna, hälso- och sjukvården och socialtjänsten. Kommunerna bör</span><span> kartlägga vilka årsrika i respektive</span><span> kommun som är i behov av tillgång till personal</span><span> som</span><span> kan teckenspråk. Kommunerna bör också se till att äldreomsorgens personal har den kunskap som behövs för att tillgodose årsrika döva personers olika behov. En teckenspråkig miljö är avgörande för deras livskvalitet och aktiva deltagande i det sociala livet. </span>\r\n\t\t\t</p>\r\n\t\t\t<h3>\r\n\t\t\t\t<span>Åldersgränsen för personlig assistans</span>\r\n\t\t\t</h3>\r\n\t\t\t<p class=\"Normalutanindragellerluft\">\r\n\t\t\t\t<span>Den övre åldersgränsen, 65 år, för att nybeviljas personlig assistans </span><span>är problematisk. Det är stor skillnad om en person får stroke med stora </span><span>behov av stöd</span><span> före eller efter 65-års</span><span>­</span><span>dagen. Sker insjuknandet efter 65-årsdagen är det hemtjänst, hemsjukvård och närståendevård som kan ges. Om personer med omfattande kroniska funktions</span><span>nedsätt</span><span>­</span><span>ningar</span><span>, t.ex. polio- och neurosedynskadade, har klarat sig själva</span><span> </span><span>fram till 65-årsdagen men därefter försämrats så får de lita till hemtjänst och närståendeinsatser.</span>\r\n\t\t\t</p>\r\n\t\t\t<p>\r\n\t\t\t\t<span>Personlig assistans innebär stor frihet för den som får det, samtidigt som det är en jämförelsevis kostnadseffektiv insats. </span><span>Vi anser </span><span>att </span><span>det bör utredas </span><span>vad det skulle innebära mänskligt och ekonomiskt med en ändring av 65-årsgränsen. </span>\r\n\t\t\t</p>\r\n\t\t\t<h2>\r\n\t\t\t\t<span>Ett bra boende</span>\r\n\t\t\t</h2>\r\n\t\t\t<p class=\"Normalutanindragellerluft\">\r\n\t\t\t\t<span>Även om de flesta människor räknar med att vilja bo kvar i sin gamla bostad hela livet ökar intresset för att flytta till något mer anpassat för funktionsnedsättningar och där man kan ha sällskap av andra och äta tillsammans. Utredningarna Bo bra hela livet (SOU 2008:113) och Bo</span><span>städer att bo kvar i (SOU 2015:</span><span>85) skrev att nu kommer en generation som är van vid ett bekvämt och självständigt liv. Därför behövs tillgång till olika bostadstyper och en förbättring av tillgängligheten i befintliga bostäd</span><span>er. En sådan som föreslogs var t</span><span>rygghetsbo</span><span>ende som är avsett</span><span> för människor som vill ha en bekväm</span><span>­</span><span>are bostad och socialt nätverk. Där ska finnas tillgång till husvärd samt möjlighet att äta tillsammans.</span>\r\n\t\t\t</p>\r\n\t\t\t<p>\r\n\t\t\t\t<span>Enligt utredningen Bostäder att b</span><span>o kvar i behöver det byggas 360</span><span> </span><span>000 fler bostäder för seniorerna fram till 2030. Enligt Boverkets statistik</span><span> januari 2018 fanns då cirka 8</span><span> </span><span>2</span><span>00 särskilda boenden. 143 kommuner ansåg att de hade tillräckligt med särskilda boenden medan oba</span><span>lans rådde i 130 kommuner. Om 2</span><span> </span><span>år räknar 173 kommuner </span><span>med </span><span>att ha full täckning. Trygghet</span><span>s</span><span>boenden fanns i 170 kommuner med totalt 9</span><span> </span><span>650 bostäder.</span><span> Seniorboendena uppgick till 12</span><span> </span><span>406 fördelade på </span><span>185 kommuner. För samtliga äldre</span><span>­</span><span>boendeformer är</span><span> lägenheterna</span><span> i princip </span><span>samtliga uthyrda eller sålda</span><span>. </span>\r\n\t\t\t</p>\r\n\t\t\t<p>\r\n\t\t\t\t<span>Ett dåligt anpassat boende kan leda till isolering och risk för allvarliga skador eller depressioner, medan ett tryggt boende förbättrar hälsan och bidrar till ett gott liv i gemenskap med andra. Detta kan i sin tur skjuta up</span><span>p tidpunkten för inträdet i det för samhället mycket kostsamma vård- </span><span>och omsorgsboendet.</span>\r\n\t\t\t</p>\r\n\t\t\t<p>\r\n\t\t\t\t<span>Att bygga bostäder som årsrika efterfrågar är ett effektivt sätt att få igång önskvärda flyttkedjor. På de platser där man har fått igång byggandet är det oftast barnfa</span><span>miljer som flyttar in i de vill</span><span>or som kommer ut på marknaden. Det är alltså bra för alla att det blir lätt att göra rationella val när det gäller boendet, oavsett vilken ålder man har uppnått. </span>\r\n\t\t\t</p>\r\n\t\t\t<p>\r\n\t\t\t\t<span>De lämpliga bostäderna måste dock vara möjliga att efterfråga för de som behöver dem. Tillgängliga bostäder finns framförallt i nyproduktion, men hyran för nyproduce</span><span>­</span><span>rade tvåor är hög</span><span> – nästan 8</span><span> </span><span>000 kr i månaden.</span><span> </span><span>I vår budgetmotion avsätter vi medel för att </span><span>stegvis </span><span>höja </span><span>taket </span><span>i bostadstillägget</span><span> </span><span>till</span><span> 7</span><span> </span><span>000 kronor. Bostadstillägget har samtidigt en avgörande betydelse för att lyfta ekonomiskt svaga pensionärer över fattigdoms</span><span>­</span><span>gränsen. Det är riktat specifikt till pensionärer med låga inkomster, som har små marginaler när hyran är betald. Eftersom kvinnor i genomsnitt har lägre pensioner än män är det också betydligt fler kvinnor än män som uppbär bostadstillägg. Liberalerna vill stärka ekonomin för denna grupp.</span>\r\n\t\t\t</p>\r\n\t\t\t<h2>\r\n\t\t\t\t<span>Bekämpa den ofrivilliga ensam</span><span>heten</span>\r\n\t\t\t</h2>\r\n\t\t\t<p class=\"Normalutanindragellerluft\">\r\n\t\t\t\t<span>Ofrivillig ensamhet orsakar stort lidande – psykiskt men även fysiskt. Social isolering är ett samhällsproblem och ett hälsoproblem som Liberalerna vill göra något åt. Det drabbar människor i alla åldrar, även ungdomar – men kanske främst årsrika människor. </span>\r\n\t\t\t</p>\r\n\t\t\t<p>\r\n\t\t\t\t<span>Ensamheten leder med tiden till kännbara fysiska och psykiska konsekvenser. Våra kroppar får svårare att hantera bakterier och virus. Fysisk smärta blir svårare. En sammanställning av 148 olika forskningsstudier visar att ofrivillig ensamhet skadar oss lika mycket som rökning och fetma. Det blir en ond cirkel, för psykisk och fysisk ohälsa leder samtidigt till ensamhet.</span><span> </span>\r\n\t\t\t</p>\r\n\t\t\t<p>\r\n\t\t\t\t<span>En viktig orsak till ensamhet är när man inte längre känner sig behövd, upplever att man inte längre är en del av samhället därför att man förlorat den sociala bas som arbetslivet ger. En annan orsak är när man förlorat sin sociala bas därför att anhöriga och vänner gått bort och man inte förmått bygga upp nya goda relationer i livet. </span>\r\n\t\t\t</p>\r\n\t\t\t<p>\r\n\t\t\t\t<span>Ensamhet kan </span><span>vara positivt</span><span> när man väljer det själv. Men den påtvingade ensam</span><span>­</span><span>heten är förödande för många. Ensamma människor som lider av brist på sociala kontakter hör till vår tids glömda Sverige. </span>\r\n\t\t\t</p>\r\n\t\t\t<p>\r\n\t\t\t\t<span>Politiker kan och ska inte skapa vänskapsband åt den som är ensam. Men genom politiska initiativ kan vi underlätta gemenskap och motverka isolering. </span>\r\n\t\t\t</p>\r\n\t\t\t<p>\r\n\t\t\t\t<span>Många av de förslag vi för fram på andra områden är viktiga också för att råda bot på ofrivillig ensamhet. Att få stanna kvar i arbetslivet så länge man önskar innebär till exempel ökade möjligheter till ett socialt sammanhang, och de förslag vi för fram i denna motion om boende för äldre bidrar till att skapa mötesplatser och bryta isolering. </span>\r\n\t\t\t</p>\r\n\t\t\t<p>\r\n\t\t\t\t<span>Men det behövs också ett tydligt och samlat initiativ. Vi vill därför se en nationell strategi som inkluderar många olika samhällssektorer som vård och omsorg, stads</span><span>­</span><span>planering, transporter, kultur, civilsamhälle, näringsliv och så vidare</span><span>, och vi avsätter medel i vår budgetmotion för detta</span><span>. Målet ska vara att minska risken för långvarig och ofrivillig ensamhet i människors liv, öka kunskapen om ofrivillig ensamhet, utveckla evidensbaserade metoder och skapa ett gemensamt engagemang i samhället mot social isolering.</span>\r\n\t\t\t</p>\r\n\t\t\t<h2>\r\n\t\t\t\t<span>Reformera äldreomsorgen</span>\r\n\t\t\t</h2>\r\n\t\t\t<p class=\"Normalutanindragellerluft\">\r\n\t\t\t\t<span>Ett område där årsrika människor i hög grad behandlats som ett kollektiv är äldreomsorgen. Samma lösningar erbjuds till alla, ofta med en förment klapp på huvudet. Årsrika människor som behöver stöd i sin vardag förutsätts varken kunna eller välja själva. Men det är ju precis tvärtom. Respekten för den enskilda människan är särskilt viktig när hon är i en utsatt situation. Alliansregeringen genomförde en rad reformer för att öka årsrika människors valfrihet och delaktighet som LOV, lagen om valfrihetssystem, som innebär att årsrika människor kan välja vilket hemtjänstföretag som ska kliva över tröskeln, och i en del kommuner också äldreboende.</span>\r\n\t\t\t</p>\r\n\t\t\t<p>\r\n\t\t\t\t<span>Under den gångna mandatperioden har valfriheten systematiskt motarbetats bland annat </span><span>genom fyrkantiga förslag om vinstbegränsningar. Syftet </span><span>sades </span><span>vara att stoppa oseriösa aktörer i välfärden. Men oseriösa aktörer ska naturligtvis inte tillåtas gå </span><span>vare sig</span><span> med vinst eller med förlust, de ska inte finnas i välfärden alls. </span><span>Vinstbegränsningar</span><span> gör ingenting för att säkr</span><span>a kvaliteten i välfärden</span><span> men skadar däremot seriösa verksamheter och de människor som behöver dem. Kvalitetskraven ska vara höga och tillsynen skarp, och den som gör ett bra jobb ska få lön för sitt arbete – också om hen äger verksamheten. </span>\r\n\t\t\t</p>\r\n\t\t\t<p>\r\n\t\t\t\t<span>Valfriheten ska inte begränsas, den ska utökas så att den är tillgänglig för fler. Vi behöver också fylla valfriheten med innehåll. Valfriheten i det stora – vem som ska utföra omsorgen – har ökat, men fyrkantig biståndsbedömning i kombination med knappa resurser och personal som inte har mandat eller kompetens att vara flexibla gör att självbestämmandet i det lilla fortfarande är alltför begränsat. Det är inte acceptabelt. Det måste vara möjligt att kombinera rättssäkerhet och kostnadskontroll med respekt för människors integritet. </span>\r\n\t\t\t</p>\r\n\t\t\t<p>\r\n\t\t\t\t<span>Självbestämmande och integritet var honnörsord redan när dåvarande socialminister Gabriel Romanus (FP) lade fram förslaget till dagens socialtjänstlag 1979. Allians</span><span>­</span><span>regeringen förtydligade detta 2011 i en ny bestämmelse i socialtjänstlagen om att den enskilde själv, så långt möjligt, ska kunna välja när och hur stöd och hjälp i boendet och annan service ska ges. Men i vardagen och praktiken behöver man ständigt återkomma till detta. </span>\r\n\t\t\t</p>\r\n\t\t\t<p>\r\n\t\t\t\t<span>Den nationella styrningen av äldreomsorgen behöver bli tydligare. Det är inte rimligt att den som bor på ena sidan en kommungräns ska få tillgång till mycket bättre hem</span><span>­</span><span>tjänst än den som råkar bo på den andra.</span>\r\n\t\t\t</p>\r\n\t\t\t<p>\r\n\t\t\t\t<span>Ett exempel på där skillnaderna är orimligt stora är äldres inflytande över vad de ska äta. God och näringsrik mat samt trivsamma måltider är en viktig kvalitetsfråga i äldreomsorgen. Ett väl fungerande förebyggande arbete mot undernäring minskar också risken för fallskador och andra hälsoproblem, samtidigt som behovet av omvårdnad minskar.</span>\r\n\t\t\t</p>\r\n\t\t\t<p>\r\n\t\t\t\t<span>Liberalerna föreslår att det ska tillhöra så kallad skälig levnadsnivå att få äta det man själv tycker om. Socialtjänstlagen bör förtydligas, och en laga-mat-garanti för hem</span><span>­</span><span>tjänsten </span><span>bör </span><span>införas. Den som har fått hjälp med måltider beviljad ska ha rätt att välja mellan att få mat lagad i det egna hemmet och att få mat levererad hem. För den mat som levereras ska det finnas flera olika leverantörer och rätter att välja mellan. Också i särskilt boende ska de äldres inflytande över måltiderna och måltidernas kvalitet öka. </span><span>I vår budgetmotion avsätter vi medel</span><span> för att kvaliteten och valfriheten vad gäller måltiderna i äldreomsorgen ska öka.</span>\r\n\t\t\t</p>\r\n\t\t\t<p>\r\n\t\t\t\t<span>Allt fler årsrika använder sig av RUT-tjänster istället för hemtjänst, om det är till exempel städning och mat de behöver hjälp med, inte omvårdnad. På så sätt får de full bestämmanderätt över vad de vill ha hjälp med, samtidigt som hemtjänsten avlastas och kan koncentrera sig på dem med stora behov. I många kommuner är också timkostnaden efter RUT-avdrag lägre än avgiften för hemtjänst. För att ge fler årsrika möjlighet att efterfråga RUT-tjänster föreslår vi därför i vår budgetmotion att skattereduktionen för RUT-tjänster höjs från 50 procent till 60 procent för personer över 80 år. </span>\r\n\t\t\t</p>\r\n\t\t\t<p>\r\n\t\t\t\t<span>Från många håll i landet hörs vittnesmål om en mycket långtgående detaljstyrning av äldreomsorgens innehåll och om omsorgspersonal och biståndsbedömare som inte vågar ändra innehållet i de planerade insatserna det minsta utan att först förankra det högre upp. Det är inte i linje med lagstiftarens intentioner. Socialtjänstlagen inte bara tillåter utan påbjuder att omsorgen ska utgå från den enskildes önskemål. </span>\r\n\t\t\t</p>\r\n\t\t\t<p>\r\n\t\t\t\t<span>Arbetsledare, chefer och ansvariga politiker måste därför vara tydliga med att medarbetarna både får och ska vara tillmötesgående. Omsorgspersonal som är utbildade för sitt arbete, är trygga i sin roll och känner att de har mandat från sin arbetsledning har lättare att själva vara flexibla. Det finns tydlig evidens för att välutbildad personal och gott ledarskap har stor betydelse för kvaliteten generellt i äldreomsorgen. </span>\r\n\t\t\t</p>\r\n\t\t\t<p>\r\n\t\t\t\t<span>En av de viktigaste kvalitetsfaktorerna i äldreomsorgen är personalens kompetens. Det gäller särskilt omvårdnadsuppgifter i hemtjänsten, där man ofta arbetar ensam med sköra äldre i deras hem, långt från ledning och chefsstöd med hemmet som arbetsplats. Då är det nödvändigt med krav på utbildning och tillräckliga språkkunskaper för att kunna dokumentera. När det inte handlar om ensamarbete kan det tvärtom vara värdefullt med en blandning av kompetenser, där kvalificerad personal utför kvalifi</span><span>­</span><span>cerade uppgifter, medan den som har liten erfarenhet eller </span><span>låg </span><span>utbildning kan avlasta</span><span> med</span><span> de enklare uppgifterna. Det är också en viktig väg in på arbetsmarknaden.</span>\r\n\t\t\t</p>\r\n\t\t\t<p>\r\n\t\t\t\t<span>Sedan 1</span><span> </span><span>januar</span><span>i 2018 gäller l</span><span>agen</span><span>(2017:612</span><span>)</span><span> om samverkan vid utskrivning från sluten hälso- och sjukvård</span><span>.</span><span> Det innebär att slutenvården, öppenvården och kommunen med hemtjänsten eller vård- och omsorgboendet ska samverka så att det blir en så bra hemkomst som möjligt. Det innebär att hälso- och sjukvården måste samverka och bör då vid prioriteringar av behov utgå från en gemensam värdegrund. Medan hälso- och sjukvårdslagen innehåller en sådan saknas den i socialtjänstlagen.</span><span> Vi </span><span>vill se en bred utredning om vårdens och omsorgens framtida prioriteringar och utvecklar detta i vår sjukvårdspolitiska motion.</span>\r\n\t\t\t</p>\r\n\t\t\t<h2>\r\n\t\t\t\t<span>Tekniska hjälpmedel</span>\r\n\t\t\t</h2>\r\n\t\t\t<p class=\"Normalutanindragellerluft\">\r\n\t\t\t\t<span>Den tekniska utvecklingen inom området välfärdsteknik går snabbt. Social</span><span>styrelsens definition här lyder ”d</span><span>igital teknik som syftar till att bibehålla eller öka trygghet, aktivitet, delaktighet eller självständighet för en person som har eller löper förhöjd risk att få en funktionsnedsättning”. Som exempel kan nämnas digitala stöd för provtagning och förmedling av provsvar, fallförebyggande insatser och automatisk övervakning i boendena.</span>\r\n\t\t\t</p>\r\n\t\t\t<p>\r\n\t\t\t\t<span>Tillgång till Skype </span><span>kan underlätta kontakt med nära och kära och därför minska känsla</span><span>n</span><span> av ensamhet och därmed höja livskvaliteten.</span>\r\n\t\t\t</p>\r\n\t\t\t<p>\r\n\t\t\t\t<span>Tekniska lösningar måste utgå från individens behov med hänsyn tagen till självbestämmande och integritet. På plussidan för teknik i individens hem är ökad trygghet och involvering av den årsrike. Det blir lättare att följa vårdplanen</span><span>,</span><span> och informationsutbytet med patienten underlättas. Åtgärder kan vidtas snabbare om värdena avviker t.ex. vid hjärtmedicinering, justering av blodtrycksmedicinering och insättande av vätskedrivande medel. På minussidan kan ligga teknikproblem, att den mobila täckningen är dålig eller att patienten blir stressad av att ta prover varje dag eller att se sena mätvärden.</span>\r\n\t\t\t</p>\r\n\t\t\t<p>\r\n\t\t\t\t<span>Statens medicinsk-etiska råd har givit ut </span><span>rapport</span><span>en</span><span> Robotar och övervakning i vården av äldre – etiska aspekter</span><span> </span><span>(2014:2)</span><span>. Här tas fram vad man ska iaktta inför införandet av tekniska hjälpmedel och automatisk övervakning i äldreomsorgen. I det sammanhanget understryks att teknik inte får vara en lösning för att avhjälpa personalbrist. Vi anser att dessa principer bör iakttas generellt vid införande av digital och annan teknik i vården och omsorgerna.</span>\r\n\t\t\t</p>\r\n\t\t\t<h2>\r\n\t\t\t\t<span>Hälso- och sjukvård för årsrika</span>\r\n\t\t\t</h2>\r\n\t\t\t<p class=\"Normalutanindragellerluft\">\r\n\t\t\t\t<span>Även om årsrika personer är friskare idag än förr kommer en dag då ohälsan slår till. För att tillgodose behoven av hälso- och sjukvård behöver primärvården utvecklas och satsa mer på att förebygga ohälsa hos äldre personer och ansvara för rehabilitering efter stroke, olycksfall m.m. Det kräver kompetens i geriatrik och gerontologi </span><span>såväl </span><span>hos de läkare som de äldre patienterna möter som hos övrig personal.</span>\r\n\t\t\t</p>\r\n\t\t\t<p>\r\n\t\t\t\t<span>Det är särskilt viktigt när det gäller de äldre personer som betecknas som multisjuka. Omkring fem procent av dem som är 75 år och äldre uppskattas vara multisjuka, d.v.s. under ett år ha vårdats på sjukhus vid tre eller fler tidpunkter och då fått tre eller fler sjukdomsdiagnoser registrerade. Den behandling de får baseras, enligt Socialstyrelsen, alltför ofta på symtom, inte på diagnos. De behandlas med en rad olika metoder vid olika tillfällen där läkemedelsbehandling är den dominerande. De har kontakt med många olika yrkesgrupper där ingen ser till helheten. </span>\r\n\t\t\t</p>\r\n\t\t\t<p>\r\n\t\t\t\t<span>I Närvård västra Skaraborg och i Tiohundra Norrtälje har kommunerna, primär</span><span>­</span><span>vården och sjukhusen en gemensam organisation och finansiering av äldresjukvården. Det har visat sig vara bättre för vårdtagare och personal, samtidigt som det kostar mindre. Det är också den organisation som föreslås i utredningen Effektiv vård (SOU 2016:2), och det bör vara en av utgångspunkterna för framtida sjukvårdsreformer.</span>\r\n\t\t\t</p>\r\n\t\t\t<h2>\r\n\t\t\t\t<span>Läkemedelsbehandling av årsrika människor</span>\r\n\t\t\t</h2>\r\n\t\t\t<p class=\"Normalutanindragellerluft\">\r\n\t\t\t\t<span>Stora insatser under många år har gjorts för att förbättra läkemedelsbehandlingen av årsrika människor</span><span>,</span><span> men vi har fortfarande problem i form av läkemedelsskador men också underbehandling till följd av felaktigt val av läkemedel, felaktiga kombinationer av läkemedel och felaktiga doseringar.</span>\r\n\t\t\t</p>\r\n\t\t\t<p>\r\n\t\t\t\t<span>Utöver fortsättning av den nationella läkemedelsstrategin (Nationell läkemedels</span><span>­</span><span>strategi </span><span>– </span><span>Handlingsplan 2014) behövs en ökning av grund- och vidareutbildningen av läkarna i ämnena geriatrik och klinisk farmakologi, men utbildningen av andra yrkesgrupper inom hälso- och sjukvården i geriatrik och läkemedelsbehandling behöver också stärkas.</span>\r\n\t\t\t</p>\r\n\t\t\t<p>\r\n\t\t\t\t<span>För att förskrivare och farmacevter ska ha tillgång till aktuella och korrekta uppgifter om en patients läkemedelsbehandling är det angeläget att arbetet med </span><span>den </span><span>nationella läkemedelslistan, beslutad av riksdagen våren 2018, förs i hamn utan dröjsmål. </span>\r\n\t\t\t</p>\r\n\t\t\t<h2>\r\n\t\t\t\t<span>Vård och omsorg vid livets slut</span>\r\n\t\t\t</h2>\r\n\t\t\t<p class=\"Normalutanindragellerluft\">\r\n\t\t\t\t<span>Forskning har visat att äldre människor vill tala om hur de vill ha sin sista levnads</span><span>­</span><span>period. Ändå undviker behandlande läkare att tala med sina åldrande patienter och deras anhöriga om deras önskemål under den sista levnadstiden. Sådana samtal skulle kunna underlätta möjligheterna till en så fridfull död som möjligt. Det är något som sjukhusens akutmottagningar knappast kan tillhandahålla. Högkvalitativ vård och omsorg i livets slutskede ska därför i möjligaste mån erbjudas i hemmet, eller i vård- och omsorg</span><span>s</span><span>­</span><span>boendet. Alla döende, oavsett ålder och bostadsort, ska vara garanterade tillgång till kvalificerad palliativ vård och inte behöva dö ensamma.</span>\r\n\t\t\t</p>\r\n\t\t\t<p>\r\n\t\t\t\t<span>Patientlagen och socialtjänstlagen bör kompletteras med krav på att vård och omsorg organiseras så att alla</span><span> som så önskar</span><span> garanteras mänsklig närvaro vid sin död. För att skapa livskvalitet i livets sista tid behöver vårdens och omsorgens arbetssätt utvecklas och formas utifrån patienternas behov. Här kan frivilligorganisationer göra en viktig insats.</span>\r\n\t\t\t</p>\r\n\t\t\t<p>\r\n\t\t\t\t<span>Svenska Läkaresällskapet och Socialstyrelsen har formulerat riktlinjer för läkares handlande i livets slutskede. De betonar att om en patient är beslutskapabel, välinfor</span><span>­</span><span>merad och införstådd med konsekvenserna av olika behandlingsalternativ ska läkaren respektera patientens önskan om att livsuppehållande behandling inte inleds och att redan inledd behandling avslutas. Detta gäller även i situationer då patienten inte befinner sig i livets slutskede och där behandling medicinskt sett skulle kunna gagna patienten. Läkaren ska alltid erbjuda adekvat palliativ behandling. För icke besluts</span><span>­</span><span>kapabla patienter ska tidigare uttryckt önskan om att avstå, påbörja eller avbryta livsuppehållande behandling respekteras. Finns ingen sådan önskan bör läkaren om möjligt samråda med närstående. </span>\r\n\t\t\t</p>\r\n\t\t\t<p>\r\n\t\t\t\t<span>Verkligheten visar att riktlinjerna inte tillämpas i tillräcklig utsträckning i vården, i den kommunala omsorgen och på akutmottagningarna. Det gäller särskilt äldre personer som närmar sig livets slut och för vilka högteknologiska medicinska insatser inte är de lämpligaste. Inte minst läkare och annan personal som arbetar i akutsjukvården behöver bättre kunskap om äldre människors behov i livets slutskede. God omvårdnad och palliativ vård skulle i stället ge en bättre livskvalitet under livets sista dagar. I dessa fall skulle tillgång till vårddirektiv vara till vägledning.</span>\r\n\t\t\t</p>\r\n\t\t\t<p>\r\n\t\t\t\t<span>År 2008 lämnade Statens medicinsk-etiska råd (Smer) över en skrivelse till reger</span><span>­</span><span>ingen om livsslutsfrågor. Rådet konstaterade att nuvarande lagstiftning ger utrymme för att avstå från att inleda livsuppehållande behandling och att avbryta sådan samt att ge s.k. palliativ sedering, dvs. att man får sova under sin sista tid. Smer framförde att patienter borde ha ett utökat inflytande över utformningen av den palliativa vården och större möjligheter att själv bestämma om och när palliativ sedering ska tillämpas.</span>\r\n\t\t\t</p>\r\n\t\t\t<p>\r\n\t\t\t\t<span>Skrivelsen föranledde inte någon åtgärd från regeringens sida. Svenska Läkare</span><span>­</span><span>sällskapet</span><span> </span><span>gick 2010 ut med Etiska riktlinjer för palliativ sedering i livets slutskede och Socialstyrelsen 2013 med Nya rekommendationer om vård i livets slutskede</span><span>,</span><span> vilket inneburit framsteg.</span>\r\n\t\t\t</p>\r\n\t\t\t<p>\r\n\t\t\t\t<span>Hösten 2017 återkom Smer genom att publicera Dödshjälp, en kunskapssamman</span><span>­</span><span>ställning (Smer 2017:2). Den innehåller en bred översyn av kunskapsläget om dödshjälp med fokus på forskning och statistik från länder och delstater som legaliserat dödshjälp i någon form. Syftet är att få frågan diskuterad i samhället och därigenom få en vägledning om hur man bör gå vidare. </span>\r\n\t\t\t</p>\r\n\t\t\t<p>\r\n\t\t\t\t<span>Den 1</span><span> </span><span>juli 2017 infördes lagstiftning om framtidsfullmakter, något som Liberalerna länge verkat för. En framtidsfullmakt innebär att en enskild individ kan välja en person att företräda honom eller henne, om han eller hon senare i livet blir beslutsoförmögen.</span>\r\n\t\t\t</p>\r\n\t\t\t<p>\r\n\t\t\t\t<span>För oss liberaler är detta en fråga om att stärka den enskildes självbestämmande över sin egen framtid. Genom framtidsfullmakter får den enskilde större makt att planera och behålla kontrollen över viktiga angelägenheter.</span>\r\n\t\t\t</p>\r\n\t\t\t<p>\r\n\t\t\t\t<span>Även om ny lagstiftning är på plats finns det dock många olösta frågor. Bland annat omfattar dessa framtidsfullmakter inte hälso- och sjukvård, vilket innebär problem inte minst i livets slutskede. Vi utvecklar våra synpunkter på framtidsfullmakter i vår familjerättsliga motion. </span>\r\n\t\t\t</p>\r\n\t\t\t<h2>\r\n\t\t\t\t<span>Motverka våld och övergrepp</span>\r\n\t\t\t</h2>\r\n\t\t\t<p class=\"Normalutanindragellerluft\">\r\n\t\t\t\t<span>Den som slår en närstående slutar inte för att hen själv eller hens partner fyllt 65. Inte sällan blir det värre då, och för andra börjar våldet och övergreppen först sent i livet – det gäller både offer och förövare. Vissa demenssjukdomar kan ge personlighetsföränd</span><span>­</span><span>ringar och aggressivitet. En utmattad anhörigvårdare kan ta ut sin frustration på den som vårdas. Den som blivit sårbar på grund av ålder och sjukdom kan lättare utnyttjas och kränkas.</span>\r\n\t\t\t</p>\r\n\t\t\t<p>\r\n\t\t\t\t<span>I den årsrika generationen är också män utsatta och våldet och övergreppen har ibland en annan karaktär än det som uppmärksammats mest, mäns våld mot kvinnor. Förövaren kan vara en partner, men det kan också vara vuxna barn eller en vårdare som står för övergreppen. Det handlar om fysiskt våld, om sexuellt våld, om kränkningar och vanvård, men också om att söner, döttrar och andra anhöriga lägger beslag på sina äldres tillgångar.</span>\r\n\t\t\t</p>\r\n\t\t\t<p>\r\n\t\t\t\t<span>I forskning om våld i nära relationer sätts den</span><span> övre åldersgränsen ofta vid 50–</span><span>60 år, och i Sverige har det fåtal studier </span><span>som </span><span>gjorts särskilt om våld mot äldre varit små. En kartläggning av Region Gotland 2012 pekade på att uppemot 15 procent av människor över 65 utsatts för våld och övergrepp främst i det egna hemmet.</span><span> </span><span>Men mörkertalet är stort. </span>\r\n\t\t\t</p>\r\n\t\t\t<p>\r\n\t\t\t\t<span>Bland människor i allmänhet finns numera en relativt stor medvetenhet om det våld som drabbar yngre och medelålders kvinnor. Våldet mot äldre vet människor mindre om, och det man inte känner till kan man inte hjälpa till att motverka. Vård och omsorg behöver till exempel ha kunskap för att skilja fallskador från skador orsakade av våld. Det behövs en bred nationell handlingsplan mot våld mot årsrika. Den som antogs 2014 handlar endast om våld och övergrepp inom vård och omsorg av äldre. Det är också viktigt att motverka, men det är bara en liten del av problemet. En riktig nationell handlingsplan mot våld mot årsrika måste självklart också omfatta polis och rätts</span><span>­</span><span>väsende. Även andra yrkesgrupper som möter äldre i sin vardag behöver kunskap o</span><span>m hur de kan upptäcka övergrepp</span><span> och hur just de kan hjälpa utifrån sin roll. De som arbetar inom hälso- och sjukvård samt inom äldreomsorgen bör därutöver ha anmäl</span><span>­</span><span>ningsskyldighet vid misstanke om våld eller övergrepp mot årsrika.</span>\r\n\t\t\t</p>\r\n\t\t\t<h2>\r\n\t\t\t\t<span>Bättre stöd till anhöriga </span>\r\n\t\t\t</h2>\r\n\t\t\t<p class=\"Normalutanindragellerluft\">\r\n\t\t\t\t<span>Uppemot 1,3 miljoner personer uppskattas ge vård och omsorg till anhöriga. Att ge omsorg </span><span>är vanligast i åldersgruppen 45–</span><span>64 år. Oftast är det en förälder so</span><span>m stöttas. Anhöriga i åldern 65–</span><span>80 år är de som ger mest omsorg i tid räknat till make/maka. Kommunernas stöd varierar. </span>\r\n\t\t\t</p>\r\n\t\t\t<p>\r\n\t\t\t\t<span>Anhöriginsatserna ska vara frivilliga och ett komplement till samhällets insatser</span><span>,</span><span> men i dagsläget tvingas många anhöriga att ta ett större ansvar för en närståendes vård och omsorg än de vill och orkar på grund av brister i det offentliga utbudet. De får inte det stöd och den avlastning som de behöver för att kunna hantera sin situation. </span>\r\n\t\t\t</p>\r\n\t\t\t<p>\r\n\t\t\t\t<span>En anhöriggrupp som ofta glöms bort är anhöriga som mist den de vårdat och som befinner sig i sorgearbete. Hälso- och sjukvården och kommunen bör här följa upp vilket stöd den anhörige behöver.</span>\r\n\t\t\t</p>\r\n\t\t\t<p>\r\n\t\t\t\t<span>Riksrevisionen kom 2014 med en rad rekommendationer som i punktform är att information och bemötande behöver förbättras, kommunernas anhörigstöd behöver utvecklas, statens styrmedel måste användas bättre, det behövs mer kunskap om anhörigomsorgen, det bör vara lättare att förena anhörigstöd med arbete </span><span>samt</span><span> landstingens uppdrag kring anhörigstöd bör bli tydligare. Vi har framfört tidigare att Riksrevisionens rekommendationer måste förverkligas men fortsätter att upprepa det därför att bristerna i anhörigstödet </span><span>fortfarande </span><span>är omfattande.</span>\r\n\t\t\t</p>\r\n\t\t\t<p style=\"-aw-sdt-tag:CC_Underskrifter; -aw-sdt-title:CC_Underskrifter\">\r\n\t\t\t\t<span> </span>\r\n\t\t\t</p>\r\n\t\t\t<p style=\"-aw-sdt-tag:CC_Underskrifter; -aw-sdt-title:CC_Underskrifter\">\r\n\t\t\t\t<span> </span>\r\n\t\t\t</p>\r\n\t\t\t<table cellspacing=\"0\" cellpadding=\"0\" style=\"border-collapse:collapse; margin-left:0pt; width:100%\">\r\n\t\t\t\t<tr>\r\n\t\t\t\t\t<td style=\"padding-left:5.4pt; padding-right:5.4pt; vertical-align:bottom; width:1%\">\r\n\t\t\t\t\t\t<p class=\"Underskrifter\" style=\"margin-top:15pt; margin-bottom:3pt; t-i:0pt; page-break-inside:avoid; line-height:15pt\">\r\n\t\t\t\t\t\t\t<span style=\"font-style:italic\">Jan Björklund (L)</span>\r\n\t\t\t\t\t\t</p>\r\n\t\t\t\t\t</td>\r\n\t\t\t\t\t<td style=\"padding-left:5.4pt; padding-right:5.4pt; vertical-align:bottom; width:1%\">\r\n\t\t\t\t\t\t<p class=\"Underskrifter\" style=\"margin-top:15pt; margin-bottom:3pt; t-i:0pt; page-break-inside:avoid; line-height:15pt\">\r\n\t\t\t\t\t\t\t<span style=\"font-style:italic\"> </span>\r\n\t\t\t\t\t\t</p>\r\n\t\t\t\t\t</td>\r\n\t\t\t\t</tr>\r\n\t\t\t\t<tr>\r\n\t\t\t\t\t<td style=\"padding-left:5.4pt; padding-right:5.4pt; vertical-align:bottom; width:1%\">\r\n\t\t\t\t\t\t<p class=\"Underskrifter\" style=\"margin-top:15pt; margin-bottom:0pt; t-i:0pt; page-break-inside:avoid; line-height:15pt\">\r\n\t\t\t\t\t\t\t<span style=\"font-style:italic\">Tina Acketoft (L)</span>\r\n\t\t\t\t\t\t</p>\r\n\t\t\t\t\t</td>\r\n\t\t\t\t\t<td style=\"padding-left:5.4pt; padding-right:5.4pt; vertical-align:bottom; width:1%\">\r\n\t\t\t\t\t\t<p class=\"Underskrifter\" style=\"margin-top:15pt; margin-bottom:0pt; t-i:0pt; page-break-inside:avoid; line-height:15pt\">\r\n\t\t\t\t\t\t\t<span style=\"font-style:italic\">Maria Arnholm (L)</span>\r\n\t\t\t\t\t\t</p>\r\n\t\t\t\t\t</td>\r\n\t\t\t\t</tr>\r\n\t\t\t\t<tr>\r\n\t\t\t\t\t<td style=\"padding-left:5.4pt; padding-right:5.4pt; vertical-align:bottom; width:1%\">\r\n\t\t\t\t\t\t<p class=\"Underskrifter\" style=\"margin-top:15pt; margin-bottom:0pt; t-i:0pt; page-break-inside:avoid; line-height:15pt\">\r\n\t\t\t\t\t\t\t<span style=\"font-style:italic\">Gulan Avci (L)</span>\r\n\t\t\t\t\t\t</p>\r\n\t\t\t\t\t</td>\r\n\t\t\t\t\t<td style=\"padding-left:5.4pt; padding-right:5.4pt; vertical-align:bottom; width:1%\">\r\n\t\t\t\t\t\t<p class=\"Underskrifter\" style=\"margin-top:15pt; margin-bottom:0pt; t-i:0pt; page-break-inside:avoid; line-height:15pt\">\r\n\t\t\t\t\t\t\t<span style=\"font-style:italic\">Juno Blom (L)</span>\r\n\t\t\t\t\t\t</p>\r\n\t\t\t\t\t</td>\r\n\t\t\t\t</tr>\r\n\t\t\t\t<tr>\r\n\t\t\t\t\t<td style=\"padding-left:5.4pt; padding-right:5.4pt; vertical-align:bottom; width:1%\">\r\n\t\t\t\t\t\t<p class=\"Underskrifter\" style=\"margin-top:15pt; margin-bottom:0pt; t-i:0pt; page-break-inside:avoid; line-height:15pt\">\r\n\t\t\t\t\t\t\t<span style=\"font-style:italic\">Emma Carlsson Löfdahl (L)</span>\r\n\t\t\t\t\t\t</p>\r\n\t\t\t\t\t</td>\r\n\t\t\t\t\t<td style=\"padding-left:5.4pt; padding-right:5.4pt; vertical-align:bottom; width:1%\">\r\n\t\t\t\t\t\t<p class=\"Underskrifter\" style=\"margin-top:15pt; margin-bottom:0pt; t-i:0pt; page-break-inside:avoid; line-height:15pt\">\r\n\t\t\t\t\t\t\t<span style=\"font-style:italic\">Bengt Eliasson (L)</span>\r\n\t\t\t\t\t\t</p>\r\n\t\t\t\t\t</td>\r\n\t\t\t\t</tr>\r\n\t\t\t\t<tr>\r\n\t\t\t\t\t<td style=\"padding-left:5.4pt; padding-right:5.4pt; vertical-align:bottom; width:1%\">\r\n\t\t\t\t\t\t<p class=\"Underskrifter\" style=\"margin-top:15pt; margin-bottom:0pt; t-i:0pt; page-break-inside:avoid; line-height:15pt\">\r\n\t\t\t\t\t\t\t<span style=\"font-style:italic\">Joar Forssell (L)</span>\r\n\t\t\t\t\t\t</p>\r\n\t\t\t\t\t</td>\r\n\t\t\t\t\t<td style=\"padding-left:5.4pt; padding-right:5.4pt; vertical-align:bottom; width:1%\">\r\n\t\t\t\t\t\t<p class=\"Underskrifter\" style=\"margin-top:15pt; margin-bottom:0pt; t-i:0pt; page-break-inside:avoid; line-height:15pt\">\r\n\t\t\t\t\t\t\t<span style=\"font-style:italic\">Helena Gellerman (L)</span>\r\n\t\t\t\t\t\t</p>\r\n\t\t\t\t\t</td>\r\n\t\t\t\t</tr>\r\n\t\t\t\t<tr>\r\n\t\t\t\t\t<td style=\"padding-left:5.4pt; padding-right:5.4pt; vertical-align:bottom; width:1%\">\r\n\t\t\t\t\t\t<p class=\"Underskrifter\" style=\"margin-top:15pt; margin-bottom:0pt; t-i:0pt; page-break-inside:avoid; line-height:15pt\">\r\n\t\t\t\t\t\t\t<span style=\"font-style:italic\">Roger Haddad (L)</span>\r\n\t\t\t\t\t\t</p>\r\n\t\t\t\t\t</td>\r\n\t\t\t\t\t<td style=\"padding-left:5.4pt; padding-right:5.4pt; vertical-align:bottom; width:1%\">\r\n\t\t\t\t\t\t<p class=\"Underskrifter\" style=\"margin-top:15pt; margin-bottom:0pt; t-i:0pt; page-break-inside:avoid; line-height:15pt\">\r\n\t\t\t\t\t\t\t<span style=\"font-style:italic\">Robert Hannah (L)</span>\r\n\t\t\t\t\t\t</p>\r\n\t\t\t\t\t</td>\r\n\t\t\t\t</tr>\r\n\t\t\t\t<tr>\r\n\t\t\t\t\t<td style=\"padding-left:5.4pt; padding-right:5.4pt; vertical-align:bottom; width:1%\">\r\n\t\t\t\t\t\t<p class=\"Underskrifter\" style=\"margin-top:15pt; margin-bottom:0pt; t-i:0pt; page-break-inside:avoid; line-height:15pt\">\r\n\t\t\t\t\t\t\t<span style=\"font-style:italic\">Fredrik Malm (L)</span>\r\n\t\t\t\t\t\t</p>\r\n\t\t\t\t\t</td>\r\n\t\t\t\t\t<td style=\"padding-left:5.4pt; padding-right:5.4pt; vertical-align:bottom; width:1%\">\r\n\t\t\t\t\t\t<p class=\"Underskrifter\" style=\"margin-top:15pt; margin-bottom:0pt; t-i:0pt; page-break-inside:avoid; line-height:15pt\">\r\n\t\t\t\t\t\t\t<span style=\"font-style:italic\">Maria Nilsson (L)</span>\r\n\t\t\t\t\t\t</p>\r\n\t\t\t\t\t</td>\r\n\t\t\t\t</tr>\r\n\t\t\t\t<tr>\r\n\t\t\t\t\t<td style=\"padding-left:5.4pt; padding-right:5.4pt; vertical-align:bottom; width:1%\">\r\n\t\t\t\t\t\t<p class=\"Underskrifter\" style=\"margin-top:15pt; margin-bottom:0pt; t-i:0pt; page-break-inside:avoid; line-height:15pt\">\r\n\t\t\t\t\t\t\t<span style=\"font-style:italic\">Lina Nordquist (L)</span>\r\n\t\t\t\t\t\t</p>\r\n\t\t\t\t\t</td>\r\n\t\t\t\t\t<td style=\"padding-left:5.4pt; padding-right:5.4pt; vertical-align:bottom; width:1%\">\r\n\t\t\t\t\t\t<p class=\"Underskrifter\" style=\"margin-top:15pt; margin-bottom:0pt; t-i:0pt; page-break-inside:avoid; line-height:15pt\">\r\n\t\t\t\t\t\t\t<span style=\"font-style:italic\">Christer Nylander (L)</span>\r\n\t\t\t\t\t\t</p>\r\n\t\t\t\t\t</td>\r\n\t\t\t\t</tr>\r\n\t\t\t\t<tr>\r\n\t\t\t\t\t<td style=\"padding-left:5.4pt; padding-right:5.4pt; vertical-align:bottom; width:1%\">\r\n\t\t\t\t\t\t<p class=\"Underskrifter\" style=\"margin-top:15pt; margin-bottom:0pt; t-i:0pt; page-break-inside:avoid; line-height:15pt\">\r\n\t\t\t\t\t\t\t<span style=\"font-style:italic\">Johan Pehrson (L)</span>\r\n\t\t\t\t\t\t</p>\r\n\t\t\t\t\t</td>\r\n\t\t\t\t\t<td style=\"padding-left:5.4pt; padding-right:5.4pt; vertical-align:bottom; width:1%\">\r\n\t\t\t\t\t\t<p class=\"Underskrifter\" style=\"margin-top:15pt; margin-bottom:0pt; t-i:0pt; page-break-inside:avoid; line-height:15pt\">\r\n\t\t\t\t\t\t\t<span style=\"font-style:italic\">Mats Persson (L)</span>\r\n\t\t\t\t\t\t</p>\r\n\t\t\t\t\t</td>\r\n\t\t\t\t</tr>\r\n\t\t\t\t<tr>\r\n\t\t\t\t\t<td style=\"padding-left:5.4pt; padding-right:5.4pt; vertical-align:bottom; width:1%\">\r\n\t\t\t\t\t\t<p class=\"Underskrifter\" style=\"margin-top:15pt; margin-bottom:0pt; t-i:0pt; page-break-inside:avoid; line-height:15pt\">\r\n\t\t\t\t\t\t\t<span style=\"font-style:italic\">Arman Teimouri (L)</span>\r\n\t\t\t\t\t\t</p>\r\n\t\t\t\t\t</td>\r\n\t\t\t\t\t<td style=\"padding-left:5.4pt; padding-right:5.4pt; vertical-align:bottom; width:1%\">\r\n\t\t\t\t\t\t<p class=\"Underskrifter\" style=\"margin-top:15pt; margin-bottom:0pt; t-i:0pt; page-break-inside:avoid; line-height:15pt\">\r\n\t\t\t\t\t\t\t<span style=\"font-style:italic\">Barbro Westerholm (L)</span>\r\n\t\t\t\t\t\t</p>\r\n\t\t\t\t\t</td>\r\n\t\t\t\t</tr>\r\n\t\t\t\t<tr>\r\n\t\t\t\t\t<td style=\"padding-left:5.4pt; padding-right:5.4pt; vertical-align:bottom; width:1%\">\r\n\t\t\t\t\t\t<p class=\"Underskrifter\" style=\"margin-top:15pt; margin-bottom:0pt; t-i:0pt; page-break-inside:avoid; line-height:15pt\">\r\n\t\t\t\t\t\t\t<span style=\"font-style:italic\">Allan Widman (L)</span>\r\n\t\t\t\t\t\t</p>\r\n\t\t\t\t\t</td>\r\n\t\t\t\t\t<td style=\"padding-left:5.4pt; padding-right:5.4pt; vertical-align:bottom; width:1%\">\r\n\t\t\t\t\t\t<p class=\"Underskrifter\" style=\"margin-top:15pt; margin-bottom:3pt; t-i:0pt; page-break-inside:avoid; line-height:15pt\">\r\n\t\t\t\t\t\t\t<span style=\"font-style:italic\"> </span>\r\n\t\t\t\t\t\t</p>\r\n\t\t\t\t\t</td>\r\n\t\t\t\t</tr>\r\n\t\t\t</table>\r\n\t\t\t<p>\r\n\t\t\t\t<span> </span>\r\n\t\t\t</p>\r\n\t\t</div>\r\n\t</div>"},"dokforslag":{"forslag":[{"nummer":"1","beteckning":null,"lydelse":"Riksdagen ställer sig bakom det som anförs i motionen om en systematisk genomgång av anmälningar om åldersdiskriminering och tillkännager detta för regeringen.","lydelse2":null,"utskottet":"Avslag","kammaren":"Avslag","behandlas_i":"2018/19:AU8","behandlas_i_punkt":null,"kammarbeslutstyp":null,"intressent":"AU","avsnitt":null,"grundforfattning":null,"andringsforfattning":null},{"nummer":"2","beteckning":null,"lydelse":"Riksdagen ställer sig bakom det som anförs i motionen om att på sikt höja gränsen för rätten att stanna kvar i arbetslivet till 71 år och tillkännager detta för regeringen.","lydelse2":null,"utskottet":"Avslag","kammaren":"Avslag","behandlas_i":"2018/19:AU9","behandlas_i_punkt":null,"kammarbeslutstyp":null,"intressent":"AU","avsnitt":null,"grundforfattning":null,"andringsforfattning":null},{"nummer":"3","beteckning":null,"lydelse":"Riksdagen ställer sig bakom det som anförs i motionen om att ökad hälsa på äldre dar bör inarbetas i strategierna för folkhälsopolitiken och tillkännager detta för regeringen.","lydelse2":null,"utskottet":"Avslag","kammaren":"Avslag","behandlas_i":"2018/19:SoU11","behandlas_i_punkt":null,"kammarbeslutstyp":null,"intressent":"SoU","avsnitt":null,"grundforfattning":null,"andringsforfattning":null},{"nummer":"4","beteckning":null,"lydelse":"Riksdagen ställer sig bakom det som anförs i motionen om att justera åldersgränserna för screeningprogram och tillkännager detta för regeringen.","lydelse2":null,"utskottet":"Avslag","kammaren":"Avslag","behandlas_i":"2018/19:SoU8","behandlas_i_punkt":null,"kammarbeslutstyp":null,"intressent":"SoU","avsnitt":null,"grundforfattning":null,"andringsforfattning":null},{"nummer":"5","beteckning":null,"lydelse":"Riksdagen ställer sig bakom det som anförs i motionen om att förbättra informationen om tandvårdsstöden och tillkännager detta för regeringen.","lydelse2":null,"utskottet":"Avslag","kammaren":"Avslag","behandlas_i":"2018/19:SoU8","behandlas_i_punkt":null,"kammarbeslutstyp":null,"intressent":"SoU","avsnitt":null,"grundforfattning":null,"andringsforfattning":null},{"nummer":"6","beteckning":null,"lydelse":"Riksdagen ställer sig bakom det som anförs i motionen om förstärkt kunskapsstyrning av äldretandvården och tillkännager detta för regeringen.","lydelse2":null,"utskottet":"Avslag","kammaren":"Avslag","behandlas_i":"2018/19:SoU8","behandlas_i_punkt":null,"kammarbeslutstyp":null,"intressent":"SoU","avsnitt":null,"grundforfattning":null,"andringsforfattning":null},{"nummer":"7","beteckning":null,"lydelse":"Riksdagen ställer sig bakom det som anförs i motionen om en översyn av tandvårdssystemet och tillkännager detta för regeringen.","lydelse2":null,"utskottet":"Avslag","kammaren":"Avslag","behandlas_i":"2018/19:SoU8","behandlas_i_punkt":null,"kammarbeslutstyp":null,"intressent":"SoU","avsnitt":null,"grundforfattning":null,"andringsforfattning":null},{"nummer":"8","beteckning":null,"lydelse":"Riksdagen ställer sig bakom det som anförs i motionen om att inflytande över måltider bör tillhöra en skälig levnadsnivå och tillkännager detta för regeringen.","lydelse2":null,"utskottet":"Avslag","kammaren":"Avslag","behandlas_i":"2018/19:SoU13","behandlas_i_punkt":null,"kammarbeslutstyp":null,"intressent":"SoU","avsnitt":null,"grundforfattning":null,"andringsforfattning":null},{"nummer":"9","beteckning":null,"lydelse":"Riksdagen ställer sig bakom det som anförs i motionen om organisationen av äldresjukvården och tillkännager detta för regeringen.","lydelse2":null,"utskottet":"Avslag","kammaren":"Avslag","behandlas_i":"2018/19:SoU13","behandlas_i_punkt":null,"kammarbeslutstyp":null,"intressent":"SoU","avsnitt":null,"grundforfattning":null,"andringsforfattning":null},{"nummer":"10","beteckning":null,"lydelse":"Riksdagen ställer sig bakom det som anförs i motionen om en nationell handlingsplan mot våld och övergrepp mot årsrika och tillkännager detta för regeringen.","lydelse2":null,"utskottet":"Avslag","kammaren":"Avslag","behandlas_i":"2018/19:SoU13","behandlas_i_punkt":null,"kammarbeslutstyp":null,"intressent":"SoU","avsnitt":null,"grundforfattning":null,"andringsforfattning":null},{"nummer":"11","beteckning":null,"lydelse":"Riksdagen ställer sig bakom det som anförs i motionen om anmälningsskyldighet vid misstanke om våld mot årsrika för personal inom vård och omsorg och tillkännager detta för regeringen.","lydelse2":null,"utskottet":"Avslag","kammaren":"Avslag","behandlas_i":"2018/19:SoU13","behandlas_i_punkt":null,"kammarbeslutstyp":null,"intressent":"SoU","avsnitt":null,"grundforfattning":null,"andringsforfattning":null},{"nummer":"12","beteckning":null,"lydelse":"Riksdagen ställer sig bakom det som anförs i motionen om förbättrat anhörigstöd och tillkännager detta för regeringen.","lydelse2":null,"utskottet":"Avslag","kammaren":"Avslag","behandlas_i":"2018/19:SoU13","behandlas_i_punkt":null,"kammarbeslutstyp":null,"intressent":"SoU","avsnitt":null,"grundforfattning":null,"andringsforfattning":null}]},"dokaktivitet":{"aktivitet":[{"kod":"INL","namn":"Inlämnad","datum":"2018-11-29 14:10:09","status":"inträffat","ordning":"0","process":"behandling"},{"kod":"Granskad","namn":"Granskad","datum":"2018-11-29 14:28:32","status":"inträffat","ordning":"0","process":"behandling"},{"kod":"HÄN","namn":"Hänvisad","datum":"2018-12-05 00:00:00","status":"inträffat","ordning":"0","process":"behandling"}]},"dokintressent":{"intressent":[{"intressent_id":"0603490586517","namn":"Jan Björklund","partibet":"L","ordning":"1","roll":"undertecknare"},{"intressent_id":"0582811195313","namn":"Tina Acketoft","partibet":"L","ordning":"2","roll":"undertecknare"},{"intressent_id":"0758652610","namn":"Maria Arnholm","partibet":"L","ordning":"3","roll":"undertecknare"},{"intressent_id":"0800956862429","namn":"Gulan Avci","partibet":"L","ordning":"4","roll":"undertecknare"},{"intressent_id":"0719332223713","namn":"Juno Blom","partibet":"L","ordning":"5","roll":"undertecknare"},{"intressent_id":"0737073162411","namn":"Emma Carlsson Löfdahl","partibet":"-","ordning":"6","roll":"undertecknare"},{"intressent_id":"0116759114313","namn":"Bengt Eliasson","partibet":"L","ordning":"7","roll":"undertecknare"},{"intressent_id":"0980092192122","namn":"Joar Forssell","partibet":"L","ordning":"8","roll":"undertecknare"},{"intressent_id":"0899169869710","namn":"Helena Gellerman","partibet":"L","ordning":"9","roll":"undertecknare"},{"intressent_id":"0308306375022","namn":"Roger Haddad","partibet":"L","ordning":"10","roll":"undertecknare"},{"intressent_id":"0223069839622","namn":"Robert Hannah","partibet":"L","ordning":"11","roll":"undertecknare"},{"intressent_id":"0766496753128","namn":"Fredrik Malm","partibet":"L","ordning":"12","roll":"undertecknare"},{"intressent_id":"0228167770927","namn":"Maria Nilsson","partibet":"L","ordning":"13","roll":"undertecknare"},{"intressent_id":"0161616238120","namn":"Lina Nordquist","partibet":"L","ordning":"14","roll":"undertecknare"},{"intressent_id":"0731442709013","namn":"Christer Nylander","partibet":"L","ordning":"15","roll":"undertecknare"},{"intressent_id":"0224712677012","namn":"Johan Pehrson","partibet":"L","ordning":"16","roll":"undertecknare"},{"intressent_id":"023767922422","namn":"Mats Persson","partibet":"L","ordning":"17","roll":"undertecknare"},{"intressent_id":"0322827326923","namn":"Arman Teimouri","partibet":"L","ordning":"18","roll":"undertecknare"},{"intressent_id":"0363228965800","namn":"Barbro Westerholm","partibet":"L","ordning":"19","roll":"undertecknare"},{"intressent_id":"0446541913415","namn":"Allan Widman","partibet":"L","ordning":"20","roll":"undertecknare"}]},"dokuppgift":{"uppgift":[{"kod":"motkat","namn":"Motionskategori","text":"Fristående motion","dok_id":"H6022039","systemdatum":"2019-06-04 15:29:44"},{"kod":"tilldelat","namn":"Tilldelat","text":"Socialutskottet","dok_id":"H6022039","systemdatum":"2019-06-04 15:29:44"},{"kod":"statustext","namn":"statustext","text":"Ärendet är avslutat","dok_id":"H6022039","systemdatum":"2019-05-16 17:25:16"}]},"dokbilaga":{"bilaga":[{"dok_id":"H6022039","titel":"Leva livet hela livet","subtitel":"av Jan Björklund m.fl. (L)","filnamn":"mot_201819__2039.docx","filstorlek":"89638","filtyp":"docx","fil_url":"http://data.riksdagen.se/fil/66B5BBF7-81D0-4E32-8BAE-5B6CAA71466F"},{"dok_id":"H6022039","titel":"Leva livet hela livet","subtitel":"av Jan Björklund m.fl. (L)","filnamn":"mot_201819__2039.pdf","filstorlek":"137252","filtyp":"pdf","fil_url":"http://data.riksdagen.se/fil/C17135F8-6DB4-4573-9308-8C3E758E697B"}]},"dokreferens":{"referens":[{"referenstyp":"behandlas_i","uppgift":"2018/19:SoU13","ref_dok_id":"H601SoU13","ref_dok_typ":"bet","ref_dok_rm":"2018/19","ref_dok_bet":"SoU13","ref_dok_titel":"Äldrefrågor","ref_dok_subtitel":null,"ref_dok_subtyp":"bet","ref_dok_dokumentnamn":"Betänkande"},{"referenstyp":"behandlas_i","uppgift":"2018/19:AU8","ref_dok_id":"H601AU8","ref_dok_typ":"bet","ref_dok_rm":"2018/19","ref_dok_bet":"AU8","ref_dok_titel":"Jämställdhet och åtgärder mot diskriminering","ref_dok_subtitel":null,"ref_dok_subtyp":"bet","ref_dok_dokumentnamn":"Betänkande"},{"referenstyp":"behandlas_i","uppgift":"2018/19:SoU11","ref_dok_id":"H601SoU11","ref_dok_typ":"bet","ref_dok_rm":"2018/19","ref_dok_bet":"SoU11","ref_dok_titel":"Folkhälsofrågor","ref_dok_subtitel":null,"ref_dok_subtyp":"bet","ref_dok_dokumentnamn":"Betänkande"},{"referenstyp":"behandlas_i","uppgift":"2018/19:AU9","ref_dok_id":"H601AU9","ref_dok_typ":"bet","ref_dok_rm":"2018/19","ref_dok_bet":"AU9","ref_dok_titel":"Arbetsrätt","ref_dok_subtitel":null,"ref_dok_subtyp":"bet","ref_dok_dokumentnamn":"Betänkande"},{"referenstyp":"behandlas_i","uppgift":"2018/19:SoU8","ref_dok_id":"H601SoU8","ref_dok_typ":"bet","ref_dok_rm":"2018/19","ref_dok_bet":"SoU8","ref_dok_titel":"Hälso- och sjukvårdsfrågor","ref_dok_subtitel":null,"ref_dok_subtyp":"bet","ref_dok_dokumentnamn":"Betänkande"}]},"debatt":null}}